{"1976":{"candidates":{"dem":"Jimmy Carter","rep":"Gerald Ford"},"counties":{"45001":{"margin":-8.79,"winner":"REP","dem_votes":11950,"rep_votes":14284,"other_votes":342,"total_votes":26576,"dem_pct":44.96,"rep_pct":53.75},"45003":{"margin":-19.51,"winner":"REP","dem_votes":8498,"rep_votes":12815,"other_votes":822,"total_votes":22135,"dem_pct":38.39,"rep_pct":57.9},"45005":{"margin":-8.98,"winner":"REP","dem_votes":22435,"rep_votes":27050,"other_votes":1928,"total_votes":51412,"dem_pct":43.64,"rep_pct":52.61},"45007":{"margin":12.12,"winner":"DEM","dem_votes":26087,"rep_votes":20298,"other_votes":1391,"total_votes":47775,"dem_pct":54.6,"rep_pct":42.49},"45009":{"margin":13.16,"winner":"DEM","dem_votes":11714,"rep_votes":8906,"other_votes":712,"total_votes":21332,"dem_pct":54.91,"rep_pct":41.75},"45011":{"margin":-33.74,"winner":"REP","dem_votes":5838,"rep_votes":12137,"other_votes":697,"total_votes":18673,"dem_pct":31.26,"rep_pct":65},"45013":{"margin":-27.52,"winner":"REP","dem_votes":11147,"rep_votes":19825,"other_votes":561,"total_votes":31533,"dem_pct":35.35,"rep_pct":62.87},"45015":{"margin":-17.74,"winner":"REP","dem_votes":13685,"rep_votes":19691,"other_votes":483,"total_votes":33859,"dem_pct":40.42,"rep_pct":58.16},"45017":{"margin":10.18,"winner":"DEM","dem_votes":10986,"rep_votes":8902,"other_votes":596,"total_votes":20484,"dem_pct":53.63,"rep_pct":43.46},"45019":{"margin":-2.8,"winner":"REP","dem_votes":12466,"rep_votes":13205,"other_votes":710,"total_votes":26381,"dem_pct":47.25,"rep_pct":50.05},"45021":{"margin":-13.74,"winner":"REP","dem_votes":11911,"rep_votes":15770,"other_votes":409,"total_votes":28090,"dem_pct":42.4,"rep_pct":56.14},"45023":{"margin":8.34,"winner":"DEM","dem_votes":14842,"rep_votes":12508,"other_votes":643,"total_votes":27993,"dem_pct":53.02,"rep_pct":44.68},"45025":{"margin":-12.03,"winner":"REP","dem_votes":8267,"rep_votes":10585,"other_votes":402,"total_votes":19254,"dem_pct":42.94,"rep_pct":54.97},"45027":{"margin":4.83,"winner":"DEM","dem_votes":11078,"rep_votes":10029,"other_votes":630,"total_votes":21737,"dem_pct":50.96,"rep_pct":46.14},"45029":{"margin":-28.07,"winner":"REP","dem_votes":15765,"rep_votes":28321,"other_votes":650,"total_votes":44735,"dem_pct":35.24,"rep_pct":63.31},"45031":{"margin":6.69,"winner":"DEM","dem_votes":13904,"rep_votes":12141,"other_votes":306,"total_votes":26351,"dem_pct":52.76,"rep_pct":46.08},"45033":{"margin":-14.57,"winner":"REP","dem_votes":21221,"rep_votes":28756,"other_votes":1744,"total_votes":51721,"dem_pct":41.03,"rep_pct":55.6},"45035":{"margin":-1.75,"winner":"REP","dem_votes":10828,"rep_votes":11226,"other_votes":610,"total_votes":22664,"dem_pct":47.78,"rep_pct":49.53},"45037":{"margin":-11.33,"winner":"REP","dem_votes":10928,"rep_votes":13848,"other_votes":993,"total_votes":25769,"dem_pct":42.41,"rep_pct":53.74},"45039":{"margin":-13.42,"winner":"REP","dem_votes":19352,"rep_votes":25502,"other_votes":960,"total_votes":45814,"dem_pct":42.24,"rep_pct":55.66},"45041":{"margin":11.91,"winner":"DEM","dem_votes":8043,"rep_votes":6291,"other_votes":377,"total_votes":14711,"dem_pct":54.67,"rep_pct":42.76},"45043":{"margin":-24.83,"winner":"REP","dem_votes":6543,"rep_votes":11075,"other_votes":637,"total_votes":18255,"dem_pct":35.84,"rep_pct":60.67},"45045":{"margin":-30.69,"winner":"REP","dem_votes":5323,"rep_votes":10296,"other_votes":589,"total_votes":16208,"dem_pct":32.84,"rep_pct":63.53},"45047":{"margin":1.18,"winner":"DEM","dem_votes":6224,"rep_votes":6073,"other_votes":462,"total_votes":12759,"dem_pct":48.78,"rep_pct":47.6},"45049":{"margin":2.67,"winner":"DEM","dem_votes":16962,"rep_votes":16050,"other_votes":1082,"total_votes":34095,"dem_pct":49.75,"rep_pct":47.08},"45051":{"margin":-10.91,"winner":"REP","dem_votes":18696,"rep_votes":23474,"other_votes":1621,"total_votes":43791,"dem_pct":42.69,"rep_pct":53.6},"45053":{"margin":-21.35,"winner":"REP","dem_votes":11813,"rep_votes":18418,"other_votes":706,"total_votes":30936,"dem_pct":38.18,"rep_pct":59.53},"45055":{"margin":-6.34,"winner":"REP","dem_votes":19240,"rep_votes":21875,"other_votes":465,"total_votes":41580,"dem_pct":46.27,"rep_pct":52.61},"45057":{"margin":-24.26,"winner":"REP","dem_votes":11125,"rep_votes":18397,"other_votes":444,"total_votes":29966,"dem_pct":37.13,"rep_pct":61.39},"45059":{"margin":-14.86,"winner":"REP","dem_votes":8357,"rep_votes":11322,"other_votes":282,"total_votes":19961,"dem_pct":41.87,"rep_pct":56.72},"45061":{"margin":-10.87,"winner":"REP","dem_votes":22315,"rep_votes":27924,"other_votes":1389,"total_votes":51628,"dem_pct":43.22,"rep_pct":54.09},"45063":{"margin":-4.54,"winner":"REP","dem_votes":9721,"rep_votes":10664,"other_votes":385,"total_votes":20771,"dem_pct":46.8,"rep_pct":51.34},"45065":{"margin":-25.79,"winner":"REP","dem_votes":6284,"rep_votes":10801,"other_votes":427,"total_votes":17511,"dem_pct":35.89,"rep_pct":61.68},"45067":{"margin":-31.48,"winner":"REP","dem_votes":13825,"rep_votes":27137,"other_votes":1319,"total_votes":42281,"dem_pct":32.7,"rep_pct":64.18},"45069":{"margin":-5.25,"winner":"REP","dem_votes":17526,"rep_votes":19540,"other_votes":1315,"total_votes":38381,"dem_pct":45.66,"rep_pct":50.91},"45071":{"margin":-19.36,"winner":"REP","dem_votes":21381,"rep_votes":31984,"other_votes":1406,"total_votes":54772,"dem_pct":39.04,"rep_pct":58.4},"45073":{"margin":-18.05,"winner":"REP","dem_votes":10661,"rep_votes":15484,"other_votes":581,"total_votes":26727,"dem_pct":39.89,"rep_pct":57.94},"45075":{"margin":15.51,"winner":"DEM","dem_votes":6768,"rep_votes":4902,"other_votes":359,"total_votes":12029,"dem_pct":56.26,"rep_pct":40.75},"45077":{"margin":-4.04,"winner":"REP","dem_votes":19777,"rep_votes":21504,"other_votes":1470,"total_votes":42751,"dem_pct":46.26,"rep_pct":50.3},"45079":{"margin":-29.72,"winner":"REP","dem_votes":3905,"rep_votes":7359,"other_votes":358,"total_votes":11622,"dem_pct":33.6,"rep_pct":63.32},"45081":{"margin":-19.78,"winner":"REP","dem_votes":21722,"rep_votes":32686,"other_votes":1014,"total_votes":55422,"dem_pct":39.19,"rep_pct":58.98},"45083":{"margin":-23.15,"winner":"REP","dem_votes":6714,"rep_votes":10887,"other_votes":420,"total_votes":18021,"dem_pct":37.26,"rep_pct":60.41},"45085":{"margin":-30.05,"winner":"REP","dem_votes":6721,"rep_votes":12581,"other_votes":199,"total_votes":19500,"dem_pct":34.46,"rep_pct":64.52},"45087":{"margin":-16.42,"winner":"REP","dem_votes":18573,"rep_votes":26165,"other_votes":1500,"total_votes":46239,"dem_pct":40.17,"rep_pct":56.59},"45089":{"margin":-21.31,"winner":"REP","dem_votes":18700,"rep_votes":29231,"other_votes":1496,"total_votes":49427,"dem_pct":37.83,"rep_pct":59.14},"45091":{"margin":-8.82,"winner":"REP","dem_votes":15346,"rep_votes":18361,"other_votes":466,"total_votes":34173,"dem_pct":44.91,"rep_pct":53.73}}},"1980":{"candidates":{"dem":"Jimmy Carter","rep":"Ronald Reagan"},"counties":{"45001":{"margin":5.41,"winner":"DEM","dem_votes":15402,"rep_votes":13790,"other_votes":602,"total_votes":29794,"dem_pct":51.7,"rep_pct":46.28},"45003":{"margin":-21.39,"winner":"REP","dem_votes":11292,"rep_votes":17718,"other_votes":1030,"total_votes":30039,"dem_pct":37.59,"rep_pct":58.98},"45005":{"margin":16.83,"winner":"DEM","dem_votes":9359,"rep_votes":6575,"other_votes":609,"total_votes":16543,"dem_pct":56.57,"rep_pct":39.74},"45007":{"margin":20.04,"winner":"DEM","dem_votes":14924,"rep_votes":9865,"other_votes":459,"total_votes":25248,"dem_pct":59.11,"rep_pct":39.07},"45009":{"margin":-12.61,"winner":"REP","dem_votes":23257,"rep_votes":30224,"other_votes":1787,"total_votes":55268,"dem_pct":42.08,"rep_pct":54.69},"45011":{"margin":4.84,"winner":"DEM","dem_votes":28801,"rep_votes":26053,"other_votes":1930,"total_votes":56784,"dem_pct":50.72,"rep_pct":45.88},"45013":{"margin":-0.07,"winner":"REP","dem_votes":11776,"rep_votes":11792,"other_votes":329,"total_votes":23897,"dem_pct":49.28,"rep_pct":49.34},"45015":{"margin":-15.18,"winner":"REP","dem_votes":8882,"rep_votes":12159,"other_votes":544,"total_votes":21585,"dem_pct":41.15,"rep_pct":56.33},"45017":{"margin":14.85,"winner":"DEM","dem_votes":17298,"rep_votes":12689,"other_votes":1045,"total_votes":31032,"dem_pct":55.74,"rep_pct":40.89},"45019":{"margin":-11.98,"winner":"REP","dem_votes":17338,"rep_votes":22216,"other_votes":1181,"total_votes":40735,"dem_pct":42.56,"rep_pct":54.54},"45021":{"margin":-17.55,"winner":"REP","dem_votes":21775,"rep_votes":31418,"other_votes":1752,"total_votes":54945,"dem_pct":39.63,"rep_pct":57.18},"45023":{"margin":5.66,"winner":"DEM","dem_votes":10097,"rep_votes":8986,"other_votes":532,"total_votes":19614,"dem_pct":51.48,"rep_pct":45.81},"45025":{"margin":6.56,"winner":"DEM","dem_votes":22715,"rep_votes":19875,"other_votes":677,"total_votes":43267,"dem_pct":52.5,"rep_pct":45.94},"45027":{"margin":0.43,"winner":"DEM","dem_votes":19931,"rep_votes":19755,"other_votes":1376,"total_votes":41063,"dem_pct":48.54,"rep_pct":48.11},"45029":{"margin":24.96,"winner":"DEM","dem_votes":24789,"rep_votes":14594,"other_votes":1467,"total_votes":40850,"dem_pct":60.68,"rep_pct":35.73},"45031":{"margin":3.4,"winner":"DEM","dem_votes":26748,"rep_votes":24955,"other_votes":1022,"total_votes":52725,"dem_pct":50.73,"rep_pct":47.33},"45033":{"margin":-14.16,"winner":"REP","dem_votes":19182,"rep_votes":25608,"other_votes":599,"total_votes":45389,"dem_pct":42.26,"rep_pct":56.42},"45035":{"margin":25.12,"winner":"DEM","dem_votes":21810,"rep_votes":12952,"other_votes":493,"total_votes":35256,"dem_pct":61.86,"rep_pct":36.74},"45037":{"margin":7.23,"winner":"DEM","dem_votes":9312,"rep_votes":8019,"other_votes":544,"total_votes":17875,"dem_pct":52.1,"rep_pct":44.86},"45039":{"margin":9.17,"winner":"DEM","dem_votes":24595,"rep_votes":20339,"other_votes":1487,"total_votes":46422,"dem_pct":52.98,"rep_pct":43.81},"45041":{"margin":25.49,"winner":"DEM","dem_votes":26986,"rep_votes":15928,"other_votes":459,"total_votes":43374,"dem_pct":62.22,"rep_pct":36.72},"45043":{"margin":-9.81,"winner":"REP","dem_votes":11179,"rep_votes":13687,"other_votes":696,"total_votes":25562,"dem_pct":43.73,"rep_pct":53.54},"45045":{"margin":-18.22,"winner":"REP","dem_votes":22531,"rep_votes":32867,"other_votes":1341,"total_votes":56739,"dem_pct":39.71,"rep_pct":57.93},"45047":{"margin":-7.26,"winner":"REP","dem_votes":23671,"rep_votes":27439,"other_votes":755,"total_votes":51865,"dem_pct":45.64,"rep_pct":52.9},"45049":{"margin":-4.03,"winner":"REP","dem_votes":20872,"rep_votes":22672,"other_votes":1128,"total_votes":44672,"dem_pct":46.72,"rep_pct":50.75},"45051":{"margin":9.2,"winner":"DEM","dem_votes":9320,"rep_votes":7700,"other_votes":594,"total_votes":17614,"dem_pct":52.91,"rep_pct":43.72},"45053":{"margin":-12.11,"winner":"REP","dem_votes":6004,"rep_votes":7698,"other_votes":289,"total_votes":13990,"dem_pct":42.91,"rep_pct":55.02},"45055":{"margin":-4.27,"winner":"REP","dem_votes":15313,"rep_votes":16735,"other_votes":1232,"total_votes":33280,"dem_pct":46.01,"rep_pct":50.28},"45057":{"margin":-17.94,"winner":"REP","dem_votes":13918,"rep_votes":20122,"other_votes":539,"total_votes":34579,"dem_pct":40.25,"rep_pct":58.19},"45059":{"margin":14.74,"winner":"DEM","dem_votes":24465,"rep_votes":18058,"other_votes":931,"total_votes":43455,"dem_pct":56.3,"rep_pct":41.56},"45061":{"margin":12.08,"winner":"DEM","dem_votes":7726,"rep_votes":6009,"other_votes":474,"total_votes":14209,"dem_pct":54.37,"rep_pct":42.29},"45063":{"margin":-3.21,"winner":"REP","dem_votes":23186,"rep_votes":24758,"other_votes":1028,"total_votes":48971,"dem_pct":47.35,"rep_pct":50.56},"45065":{"margin":1.35,"winner":"DEM","dem_votes":18225,"rep_votes":17726,"other_votes":910,"total_votes":36861,"dem_pct":49.44,"rep_pct":48.09},"45067":{"margin":5.35,"winner":"DEM","dem_votes":9993,"rep_votes":8957,"other_votes":425,"total_votes":19376,"dem_pct":51.58,"rep_pct":46.23},"45069":{"margin":-27.36,"winner":"REP","dem_votes":6327,"rep_votes":11342,"other_votes":666,"total_votes":18335,"dem_pct":34.51,"rep_pct":61.86},"45071":{"margin":-13.81,"winner":"REP","dem_votes":14134,"rep_votes":18755,"other_votes":583,"total_votes":33472,"dem_pct":42.23,"rep_pct":56.03},"45073":{"margin":-2.92,"winner":"REP","dem_votes":8822,"rep_votes":9366,"other_votes":464,"total_votes":18652,"dem_pct":47.3,"rep_pct":50.22},"45075":{"margin":-8.58,"winner":"REP","dem_votes":11649,"rep_votes":13863,"other_votes":294,"total_votes":25806,"dem_pct":45.14,"rep_pct":53.72},"45077":{"margin":-5.85,"winner":"REP","dem_votes":17021,"rep_votes":19176,"other_votes":672,"total_votes":36868,"dem_pct":46.17,"rep_pct":52.01},"45079":{"margin":-13.25,"winner":"REP","dem_votes":7607,"rep_votes":9999,"other_votes":438,"total_votes":18044,"dem_pct":42.16,"rep_pct":55.41},"45081":{"margin":7.51,"winner":"DEM","dem_votes":13136,"rep_votes":11261,"other_votes":557,"total_votes":24954,"dem_pct":52.64,"rep_pct":45.13},"45083":{"margin":4,"winner":"DEM","dem_votes":5417,"rep_votes":4991,"other_votes":233,"total_votes":10641,"dem_pct":50.91,"rep_pct":46.9},"45085":{"margin":-9.3,"winner":"REP","dem_votes":5047,"rep_votes":6120,"other_votes":374,"total_votes":11541,"dem_pct":43.73,"rep_pct":53.03},"45087":{"margin":12.39,"winner":"DEM","dem_votes":30107,"rep_votes":23338,"other_votes":1198,"total_votes":54643,"dem_pct":55.1,"rep_pct":42.71},"45089":{"margin":1.01,"winner":"DEM","dem_votes":16221,"rep_votes":15887,"other_votes":1037,"total_votes":33144,"dem_pct":48.94,"rep_pct":47.93},"45091":{"margin":4.99,"winner":"DEM","dem_votes":12898,"rep_votes":11632,"other_votes":879,"total_votes":25409,"dem_pct":50.76,"rep_pct":45.78}}},"1984":{"candidates":{"dem":"Walter Mondale","rep":"Ronald Reagan"},"counties":{"45001":{"margin":-21.63,"winner":"REP","dem_votes":17561,"rep_votes":27449,"other_votes":712,"total_votes":45722,"dem_pct":38.41,"rep_pct":60.04},"45003":{"margin":-39.77,"winner":"REP","dem_votes":5479,"rep_votes":12842,"other_votes":192,"total_votes":18513,"dem_pct":29.6,"rep_pct":69.37},"45005":{"margin":-12.08,"winner":"REP","dem_votes":8987,"rep_votes":11571,"other_votes":840,"total_votes":21399,"dem_pct":42,"rep_pct":54.07},"45007":{"margin":-34.86,"winner":"REP","dem_votes":9119,"rep_votes":19406,"other_votes":982,"total_votes":29507,"dem_pct":30.9,"rep_pct":65.77},"45009":{"margin":-39.62,"winner":"REP","dem_votes":8912,"rep_votes":21131,"other_votes":796,"total_votes":30839,"dem_pct":28.9,"rep_pct":68.52},"45011":{"margin":-3.32,"winner":"REP","dem_votes":24775,"rep_votes":26540,"other_votes":1811,"total_votes":53125,"dem_pct":46.63,"rep_pct":49.96},"45013":{"margin":-21.62,"winner":"REP","dem_votes":13818,"rep_votes":21741,"other_votes":1082,"total_votes":36640,"dem_pct":37.71,"rep_pct":59.34},"45015":{"margin":-22.96,"winner":"REP","dem_votes":8133,"rep_votes":13101,"other_votes":405,"total_votes":21639,"dem_pct":37.58,"rep_pct":60.54},"45017":{"margin":-6.45,"winner":"REP","dem_votes":22864,"rep_votes":26149,"other_votes":1929,"total_votes":50943,"dem_pct":44.88,"rep_pct":51.33},"45019":{"margin":-27.6,"winner":"REP","dem_votes":17680,"rep_votes":31472,"other_votes":810,"total_votes":49962,"dem_pct":35.39,"rep_pct":62.99},"45021":{"margin":-38.51,"winner":"REP","dem_votes":11455,"rep_votes":26570,"other_votes":1227,"total_votes":39252,"dem_pct":29.18,"rep_pct":67.69},"45023":{"margin":-24.93,"winner":"REP","dem_votes":18157,"rep_votes":30675,"other_votes":1375,"total_votes":50207,"dem_pct":36.17,"rep_pct":61.1},"45025":{"margin":-41.61,"winner":"REP","dem_votes":16554,"rep_votes":41593,"other_votes":2021,"total_votes":60168,"dem_pct":27.51,"rep_pct":69.13},"45027":{"margin":-14.29,"winner":"REP","dem_votes":23168,"rep_votes":31123,"other_votes":1393,"total_votes":55684,"dem_pct":41.61,"rep_pct":55.89},"45029":{"margin":-40.36,"winner":"REP","dem_votes":9239,"rep_votes":22154,"other_votes":611,"total_votes":32004,"dem_pct":28.87,"rep_pct":69.22},"45031":{"margin":-3.99,"winner":"REP","dem_votes":15159,"rep_votes":16447,"other_votes":627,"total_votes":32234,"dem_pct":47.03,"rep_pct":51.02},"45033":{"margin":-26.64,"winner":"REP","dem_votes":19067,"rep_votes":33157,"other_votes":656,"total_votes":52881,"dem_pct":36.06,"rep_pct":62.7},"45035":{"margin":-5.78,"winner":"REP","dem_votes":24378,"rep_votes":27452,"other_votes":1349,"total_votes":53179,"dem_pct":45.84,"rep_pct":51.62},"45037":{"margin":-26.78,"winner":"REP","dem_votes":14315,"rep_votes":25103,"other_votes":859,"total_votes":40277,"dem_pct":35.54,"rep_pct":62.33},"45039":{"margin":-12.41,"winner":"REP","dem_votes":20509,"rep_votes":26534,"other_votes":1525,"total_votes":48567,"dem_pct":42.23,"rep_pct":54.63},"45041":{"margin":-30.44,"winner":"REP","dem_votes":4730,"rep_votes":8971,"other_votes":230,"total_votes":13932,"dem_pct":33.95,"rep_pct":64.39},"45043":{"margin":-41.55,"winner":"REP","dem_votes":15578,"rep_votes":38801,"other_votes":1511,"total_votes":55890,"dem_pct":27.87,"rep_pct":69.42},"45045":{"margin":-43.4,"winner":"REP","dem_votes":16143,"rep_votes":42435,"other_votes":2007,"total_votes":60585,"dem_pct":26.65,"rep_pct":70.04},"45047":{"margin":-34.99,"winner":"REP","dem_votes":10684,"rep_votes":22657,"other_votes":881,"total_votes":34222,"dem_pct":31.22,"rep_pct":66.21},"45049":{"margin":-42.58,"winner":"REP","dem_votes":12237,"rep_votes":31330,"other_votes":1270,"total_votes":44837,"dem_pct":27.29,"rep_pct":69.88},"45051":{"margin":-7,"winner":"REP","dem_votes":26770,"rep_votes":30953,"other_votes":2061,"total_votes":59783,"dem_pct":44.78,"rep_pct":51.77},"45053":{"margin":-7.33,"winner":"REP","dem_votes":20672,"rep_votes":24034,"other_votes":1147,"total_votes":45853,"dem_pct":45.08,"rep_pct":52.42},"45055":{"margin":-12.35,"winner":"REP","dem_votes":16419,"rep_votes":21170,"other_votes":876,"total_votes":38465,"dem_pct":42.69,"rep_pct":55.04},"45057":{"margin":-28.84,"winner":"REP","dem_votes":8937,"rep_votes":16331,"other_votes":367,"total_votes":25635,"dem_pct":34.86,"rep_pct":63.7},"45059":{"margin":-41.63,"winner":"REP","dem_votes":11226,"rep_votes":27954,"other_votes":1003,"total_votes":40183,"dem_pct":27.94,"rep_pct":69.57},"45061":{"margin":-43.76,"winner":"REP","dem_votes":14926,"rep_votes":39196,"other_votes":1341,"total_votes":55463,"dem_pct":26.91,"rep_pct":70.67},"45063":{"margin":-31.09,"winner":"REP","dem_votes":15823,"rep_votes":30715,"other_votes":1364,"total_votes":47903,"dem_pct":33.03,"rep_pct":64.12},"45065":{"margin":-10.94,"winner":"REP","dem_votes":12252,"rep_votes":15310,"other_votes":373,"total_votes":27935,"dem_pct":43.86,"rep_pct":54.8},"45067":{"margin":-18.78,"winner":"REP","dem_votes":22258,"rep_votes":32693,"other_votes":619,"total_votes":55571,"dem_pct":40.05,"rep_pct":58.83},"45069":{"margin":-27.02,"winner":"REP","dem_votes":12363,"rep_votes":21760,"other_votes":651,"total_votes":34774,"dem_pct":35.55,"rep_pct":62.57},"45071":{"margin":-20.15,"winner":"REP","dem_votes":16050,"rep_votes":24298,"other_votes":572,"total_votes":40920,"dem_pct":39.22,"rep_pct":59.38},"45073":{"margin":-9.99,"winner":"REP","dem_votes":11850,"rep_votes":14592,"other_votes":999,"total_votes":27441,"dem_pct":43.19,"rep_pct":53.18},"45075":{"margin":-22.99,"winner":"REP","dem_votes":18914,"rep_votes":30824,"other_votes":2059,"total_votes":51798,"dem_pct":36.52,"rep_pct":59.51},"45077":{"margin":-9.26,"winner":"REP","dem_votes":13318,"rep_votes":16105,"other_votes":681,"total_votes":30104,"dem_pct":44.24,"rep_pct":53.5},"45079":{"margin":-2.52,"winner":"REP","dem_votes":19618,"rep_votes":20642,"other_votes":424,"total_votes":40684,"dem_pct":48.22,"rep_pct":50.74},"45081":{"margin":-1.1,"winner":"REP","dem_votes":28254,"rep_votes":28893,"other_votes":724,"total_votes":57872,"dem_pct":48.82,"rep_pct":49.93},"45083":{"margin":-24.43,"winner":"REP","dem_votes":8249,"rep_votes":13720,"other_votes":421,"total_votes":22389,"dem_pct":36.84,"rep_pct":61.28},"45085":{"margin":-24.75,"winner":"REP","dem_votes":16394,"rep_votes":27529,"other_votes":1069,"total_votes":44992,"dem_pct":36.44,"rep_pct":61.19},"45087":{"margin":-12.28,"winner":"REP","dem_votes":10919,"rep_votes":14123,"other_votes":1042,"total_votes":26084,"dem_pct":41.86,"rep_pct":54.14},"45089":{"margin":-31.93,"winner":"REP","dem_votes":10443,"rep_votes":20487,"other_votes":525,"total_votes":31455,"dem_pct":33.2,"rep_pct":65.13},"45091":{"margin":-13.9,"winner":"REP","dem_votes":22055,"rep_votes":29312,"other_votes":825,"total_votes":52192,"dem_pct":42.26,"rep_pct":56.16}}},"1988":{"candidates":{"dem":"Michael Dukakis","rep":"George H.W. Bush"},"counties":{"45001":{"margin":-34.82,"winner":"REP","dem_votes":3625,"rep_votes":7664,"other_votes":312,"total_votes":11601,"dem_pct":31.25,"rep_pct":66.07},"45003":{"margin":-35.03,"winner":"REP","dem_votes":9264,"rep_votes":19475,"other_votes":410,"total_votes":29149,"dem_pct":31.78,"rep_pct":66.81},"45005":{"margin":-40.29,"winner":"REP","dem_votes":11272,"rep_votes":27358,"other_votes":1295,"total_votes":39925,"dem_pct":28.23,"rep_pct":68.52},"45007":{"margin":-11.31,"winner":"REP","dem_votes":25672,"rep_votes":32359,"other_votes":1103,"total_votes":59134,"dem_pct":43.41,"rep_pct":54.72},"45009":{"margin":-36.93,"winner":"REP","dem_votes":4338,"rep_votes":9523,"other_votes":179,"total_votes":14040,"dem_pct":30.9,"rep_pct":67.83},"45011":{"margin":-36.52,"winner":"REP","dem_votes":12833,"rep_votes":28462,"other_votes":1506,"total_votes":42801,"dem_pct":29.98,"rep_pct":66.5},"45013":{"margin":-35.54,"winner":"REP","dem_votes":4357,"rep_votes":9442,"other_votes":510,"total_votes":14309,"dem_pct":30.45,"rep_pct":65.99},"45015":{"margin":-39.66,"winner":"REP","dem_votes":16205,"rep_votes":38564,"other_votes":1608,"total_votes":56377,"dem_pct":28.74,"rep_pct":68.4},"45017":{"margin":-26.33,"winner":"REP","dem_votes":10654,"rep_votes":18585,"other_votes":884,"total_votes":30123,"dem_pct":35.37,"rep_pct":61.7},"45019":{"margin":-14.58,"winner":"REP","dem_votes":26165,"rep_votes":35428,"other_votes":1958,"total_votes":63550,"dem_pct":41.17,"rep_pct":55.75},"45021":{"margin":-9.66,"winner":"REP","dem_votes":26022,"rep_votes":31706,"other_votes":1110,"total_votes":58838,"dem_pct":44.23,"rep_pct":53.89},"45023":{"margin":-12.9,"winner":"REP","dem_votes":18339,"rep_votes":23850,"other_votes":525,"total_votes":42714,"dem_pct":42.93,"rep_pct":55.84},"45025":{"margin":-12.6,"winner":"REP","dem_votes":14006,"rep_votes":18140,"other_votes":670,"total_votes":32816,"dem_pct":42.68,"rep_pct":55.28},"45027":{"margin":-40.96,"winner":"REP","dem_votes":6776,"rep_votes":16801,"other_votes":896,"total_votes":24473,"dem_pct":27.69,"rep_pct":68.65},"45029":{"margin":-39.54,"winner":"REP","dem_votes":12292,"rep_votes":29240,"other_votes":1332,"total_votes":42864,"dem_pct":28.68,"rep_pct":68.22},"45031":{"margin":-21.64,"winner":"REP","dem_votes":17191,"rep_votes":26967,"other_votes":1012,"total_votes":45170,"dem_pct":38.06,"rep_pct":59.7},"45033":{"margin":-2.07,"winner":"REP","dem_votes":19672,"rep_votes":20538,"other_votes":1543,"total_votes":41753,"dem_pct":47.11,"rep_pct":49.19},"45035":{"margin":-45.7,"winner":"REP","dem_votes":10615,"rep_votes":29615,"other_votes":1348,"total_votes":41578,"dem_pct":25.53,"rep_pct":71.23},"45037":{"margin":-43.82,"winner":"REP","dem_votes":16738,"rep_votes":43655,"other_votes":1034,"total_votes":61428,"dem_pct":27.25,"rep_pct":71.07},"45039":{"margin":-12.38,"winner":"REP","dem_votes":12097,"rep_votes":15640,"other_votes":885,"total_votes":28622,"dem_pct":42.26,"rep_pct":54.64},"45041":{"margin":-18.38,"winner":"REP","dem_votes":14504,"rep_votes":21229,"other_votes":849,"total_votes":36583,"dem_pct":39.65,"rep_pct":58.03},"45043":{"margin":-12.11,"winner":"REP","dem_votes":19439,"rep_votes":24997,"other_votes":1479,"total_votes":45914,"dem_pct":42.34,"rep_pct":54.44},"45045":{"margin":-0.76,"winner":"REP","dem_votes":21878,"rep_votes":22223,"other_votes":1266,"total_votes":45368,"dem_pct":48.22,"rep_pct":48.98},"45047":{"margin":-37.75,"winner":"REP","dem_votes":6993,"rep_votes":15734,"other_votes":430,"total_votes":23157,"dem_pct":30.2,"rep_pct":67.95},"45049":{"margin":-4.43,"winner":"REP","dem_votes":26195,"rep_votes":28730,"other_votes":2255,"total_votes":57180,"dem_pct":45.81,"rep_pct":50.24},"45051":{"margin":-9.37,"winner":"REP","dem_votes":20104,"rep_votes":24384,"other_votes":1212,"total_votes":45700,"dem_pct":43.99,"rep_pct":53.36},"45053":{"margin":-18.4,"winner":"REP","dem_votes":7355,"rep_votes":10742,"other_votes":313,"total_votes":18410,"dem_pct":39.95,"rep_pct":58.35},"45055":{"margin":-37.93,"winner":"REP","dem_votes":7037,"rep_votes":15953,"other_votes":518,"total_votes":23508,"dem_pct":29.93,"rep_pct":67.86},"45057":{"margin":-46.6,"winner":"REP","dem_votes":5371,"rep_votes":15366,"other_votes":710,"total_votes":21447,"dem_pct":25.04,"rep_pct":71.65},"45059":{"margin":-38.93,"winner":"REP","dem_votes":8495,"rep_votes":19845,"other_votes":814,"total_votes":29154,"dem_pct":29.14,"rep_pct":68.07},"45061":{"margin":-9.51,"winner":"REP","dem_votes":14269,"rep_votes":17402,"other_votes":1261,"total_votes":32931,"dem_pct":43.33,"rep_pct":52.84},"45063":{"margin":-5.4,"winner":"REP","dem_votes":7536,"rep_votes":8423,"other_votes":462,"total_votes":16422,"dem_pct":45.89,"rep_pct":51.29},"45065":{"margin":-14.6,"winner":"REP","dem_votes":17223,"rep_votes":23287,"other_votes":1026,"total_votes":41536,"dem_pct":41.47,"rep_pct":56.07},"45067":{"margin":-7.04,"winner":"REP","dem_votes":16841,"rep_votes":19482,"other_votes":1176,"total_votes":37499,"dem_pct":44.91,"rep_pct":51.95},"45069":{"margin":-25.64,"winner":"REP","dem_votes":8460,"rep_votes":14613,"other_votes":921,"total_votes":23995,"dem_pct":35.26,"rep_pct":60.9},"45071":{"margin":-37.03,"winner":"REP","dem_votes":12152,"rep_votes":26944,"other_votes":850,"total_votes":39946,"dem_pct":30.42,"rep_pct":67.45},"45073":{"margin":-19.02,"winner":"REP","dem_votes":18436,"rep_votes":27390,"other_votes":1244,"total_votes":47070,"dem_pct":39.17,"rep_pct":58.19},"45075":{"margin":-32.72,"winner":"REP","dem_votes":7125,"rep_votes":14405,"other_votes":719,"total_votes":22249,"dem_pct":32.02,"rep_pct":64.74},"45077":{"margin":-36.94,"winner":"REP","dem_votes":4507,"rep_votes":9886,"other_votes":172,"total_votes":14565,"dem_pct":30.94,"rep_pct":67.88},"45079":{"margin":-45.86,"winner":"REP","dem_votes":4144,"rep_votes":11363,"other_votes":235,"total_votes":15742,"dem_pct":26.32,"rep_pct":72.19},"45081":{"margin":-38.23,"winner":"REP","dem_votes":17000,"rep_votes":39055,"other_votes":1628,"total_votes":57683,"dem_pct":29.47,"rep_pct":67.71},"45083":{"margin":-15.8,"winner":"REP","dem_votes":24096,"rep_votes":33535,"other_votes":2117,"total_votes":59748,"dem_pct":40.33,"rep_pct":56.13},"45085":{"margin":-10.73,"winner":"REP","dem_votes":19538,"rep_votes":24295,"other_votes":495,"total_votes":44328,"dem_pct":44.08,"rep_pct":54.81},"45087":{"margin":-24.83,"winner":"REP","dem_votes":15189,"rep_votes":25641,"other_votes":1270,"total_votes":42099,"dem_pct":36.08,"rep_pct":60.91},"45089":{"margin":-2.41,"winner":"REP","dem_votes":29885,"rep_votes":31402,"other_votes":1554,"total_votes":62840,"dem_pct":47.56,"rep_pct":49.97},"45091":{"margin":-18.92,"winner":"REP","dem_votes":10738,"rep_votes":15941,"other_votes":820,"total_votes":27499,"dem_pct":39.05,"rep_pct":57.97}}},"1992":{"candidates":{"dem":"Bill Clinton","rep":"George H.W. Bush"},"counties":{"45001":{"margin":15.08,"winner":"DEM","dem_votes":20123,"rep_votes":14729,"other_votes":925,"total_votes":35777,"dem_pct":56.25,"rep_pct":41.17},"45003":{"margin":16.05,"winner":"DEM","dem_votes":20651,"rep_votes":14779,"other_votes":1169,"total_votes":36599,"dem_pct":56.43,"rep_pct":40.38},"45005":{"margin":15,"winner":"DEM","dem_votes":8516,"rep_votes":6272,"other_votes":175,"total_votes":14963,"dem_pct":56.92,"rep_pct":41.92},"45007":{"margin":-12.31,"winner":"REP","dem_votes":26918,"rep_votes":34756,"other_votes":2010,"total_votes":63685,"dem_pct":42.27,"rep_pct":54.58},"45009":{"margin":6.11,"winner":"DEM","dem_votes":16968,"rep_votes":14967,"other_votes":795,"total_votes":32730,"dem_pct":51.84,"rep_pct":45.73},"45011":{"margin":10.05,"winner":"DEM","dem_votes":15443,"rep_votes":12527,"other_votes":1045,"total_votes":29015,"dem_pct":53.22,"rep_pct":43.17},"45013":{"margin":-18.31,"winner":"REP","dem_votes":5455,"rep_votes":8018,"other_votes":526,"total_votes":13999,"dem_pct":38.96,"rep_pct":57.28},"45015":{"margin":-22.44,"winner":"REP","dem_votes":6272,"rep_votes":9959,"other_votes":200,"total_votes":16431,"dem_pct":38.17,"rep_pct":60.61},"45017":{"margin":-1.72,"winner":"REP","dem_votes":23822,"rep_votes":24682,"other_votes":1411,"total_votes":49915,"dem_pct":47.72,"rep_pct":49.45},"45019":{"margin":-21.74,"winner":"REP","dem_votes":6919,"rep_votes":10921,"other_votes":565,"total_votes":18406,"dem_pct":37.59,"rep_pct":59.34},"45021":{"margin":-14.32,"winner":"REP","dem_votes":5796,"rep_votes":7800,"other_votes":396,"total_votes":13992,"dem_pct":41.42,"rep_pct":55.74},"45023":{"margin":-22.44,"winner":"REP","dem_votes":9534,"rep_votes":15139,"other_votes":306,"total_votes":24980,"dem_pct":38.17,"rep_pct":60.61},"45025":{"margin":-17.74,"winner":"REP","dem_votes":19773,"rep_votes":28674,"other_votes":1733,"total_votes":50180,"dem_pct":39.4,"rep_pct":57.14},"45027":{"margin":-16.91,"winner":"REP","dem_votes":15127,"rep_votes":21426,"other_votes":706,"total_votes":37259,"dem_pct":40.6,"rep_pct":57.51},"45029":{"margin":-10.08,"winner":"REP","dem_votes":23549,"rep_votes":28973,"other_votes":1275,"total_votes":53797,"dem_pct":43.77,"rep_pct":53.86},"45031":{"margin":-12.05,"winner":"REP","dem_votes":16566,"rep_votes":21256,"other_votes":1095,"total_votes":38917,"dem_pct":42.57,"rep_pct":54.62},"45033":{"margin":13.35,"winner":"DEM","dem_votes":29409,"rep_votes":22415,"other_votes":557,"total_votes":52381,"dem_pct":56.15,"rep_pct":42.79},"45035":{"margin":17.43,"winner":"DEM","dem_votes":15210,"rep_votes":10561,"other_votes":909,"total_votes":26680,"dem_pct":57.01,"rep_pct":39.58},"45037":{"margin":12.91,"winner":"DEM","dem_votes":13793,"rep_votes":10530,"other_votes":948,"total_votes":25271,"dem_pct":54.58,"rep_pct":41.67},"45039":{"margin":-4.8,"winner":"REP","dem_votes":15505,"rep_votes":17098,"other_votes":553,"total_votes":33156,"dem_pct":46.76,"rep_pct":51.57},"45041":{"margin":8.4,"winner":"DEM","dem_votes":34543,"rep_votes":29018,"other_votes":2210,"total_votes":65771,"dem_pct":52.52,"rep_pct":44.12},"45043":{"margin":-0.42,"winner":"REP","dem_votes":10573,"rep_votes":10664,"other_votes":231,"total_votes":21467,"dem_pct":49.25,"rep_pct":49.68},"45045":{"margin":-8.42,"winner":"REP","dem_votes":13889,"rep_votes":16484,"other_votes":457,"total_votes":30830,"dem_pct":45.05,"rep_pct":53.47},"45047":{"margin":-13.28,"winner":"REP","dem_votes":19901,"rep_votes":26091,"other_votes":616,"total_votes":46608,"dem_pct":42.7,"rep_pct":55.98},"45049":{"margin":1.37,"winner":"DEM","dem_votes":8515,"rep_votes":8277,"other_votes":639,"total_votes":17431,"dem_pct":48.85,"rep_pct":47.48},"45051":{"margin":-10.19,"winner":"REP","dem_votes":13840,"rep_votes":17104,"other_votes":1089,"total_votes":32033,"dem_pct":43.21,"rep_pct":53.39},"45053":{"margin":21.36,"winner":"DEM","dem_votes":32351,"rep_votes":20865,"other_votes":557,"total_votes":53773,"dem_pct":60.16,"rep_pct":38.8},"45055":{"margin":3.06,"winner":"DEM","dem_votes":30462,"rep_votes":28603,"other_votes":1657,"total_votes":60722,"dem_pct":50.17,"rep_pct":47.1},"45057":{"margin":-4.4,"winner":"REP","dem_votes":9709,"rep_votes":10628,"other_votes":561,"total_votes":20898,"dem_pct":46.46,"rep_pct":50.86},"45059":{"margin":11.31,"winner":"DEM","dem_votes":18991,"rep_votes":15076,"other_votes":548,"total_votes":34616,"dem_pct":54.86,"rep_pct":43.55},"45061":{"margin":-14.56,"winner":"REP","dem_votes":7014,"rep_votes":9491,"other_votes":518,"total_votes":17023,"dem_pct":41.2,"rep_pct":55.76},"45063":{"margin":16.3,"winner":"DEM","dem_votes":14425,"rep_votes":10336,"other_votes":322,"total_votes":25083,"dem_pct":57.51,"rep_pct":41.21},"45065":{"margin":7.77,"winner":"DEM","dem_votes":13735,"rep_votes":11686,"other_votes":933,"total_votes":26353,"dem_pct":52.12,"rep_pct":44.34},"45067":{"margin":-14.52,"winner":"REP","dem_votes":5080,"rep_votes":6883,"other_votes":453,"total_votes":12416,"dem_pct":40.92,"rep_pct":55.44},"45069":{"margin":13.32,"winner":"DEM","dem_votes":28702,"rep_votes":21775,"other_votes":1513,"total_votes":51990,"dem_pct":55.21,"rep_pct":41.88},"45071":{"margin":-2.01,"winner":"REP","dem_votes":16144,"rep_votes":16819,"other_votes":690,"total_votes":33654,"dem_pct":47.97,"rep_pct":49.98},"45073":{"margin":-5.97,"winner":"REP","dem_votes":13147,"rep_votes":14843,"other_votes":423,"total_votes":28413,"dem_pct":46.27,"rep_pct":52.24},"45075":{"margin":-0.02,"winner":"REP","dem_votes":20573,"rep_votes":20580,"other_votes":1331,"total_votes":42484,"dem_pct":48.43,"rep_pct":48.44},"45077":{"margin":-0.54,"winner":"REP","dem_votes":9131,"rep_votes":9233,"other_votes":440,"total_votes":18804,"dem_pct":48.56,"rep_pct":49.1},"45079":{"margin":-3.8,"winner":"REP","dem_votes":19981,"rep_votes":21584,"other_votes":589,"total_votes":42154,"dem_pct":47.4,"rep_pct":51.2},"45081":{"margin":-20.61,"winner":"REP","dem_votes":7154,"rep_votes":10966,"other_votes":372,"total_votes":18492,"dem_pct":38.69,"rep_pct":59.3},"45083":{"margin":5.15,"winner":"DEM","dem_votes":16400,"rep_votes":14773,"other_votes":406,"total_votes":31579,"dem_pct":51.93,"rep_pct":46.78},"45085":{"margin":8.39,"winner":"DEM","dem_votes":10085,"rep_votes":8493,"other_votes":399,"total_votes":18977,"dem_pct":53.15,"rep_pct":44.75},"45087":{"margin":2.22,"winner":"DEM","dem_votes":17173,"rep_votes":16413,"other_votes":678,"total_votes":34263,"dem_pct":50.12,"rep_pct":47.9},"45089":{"margin":-18.99,"winner":"REP","dem_votes":17561,"rep_votes":26063,"other_votes":1149,"total_votes":44774,"dem_pct":39.22,"rep_pct":58.21},"45091":{"margin":11.85,"winner":"DEM","dem_votes":23949,"rep_votes":18775,"other_votes":959,"total_votes":43683,"dem_pct":54.83,"rep_pct":42.98}}},"1996":{"candidates":{"dem":"Bill Clinton","rep":"Bob Dole"},"counties":{"45001":{"margin":-23.41,"winner":"REP","dem_votes":6579,"rep_votes":10788,"other_votes":613,"total_votes":17981,"dem_pct":36.59,"rep_pct":60},"45003":{"margin":-12.19,"winner":"REP","dem_votes":15637,"rep_votes":20047,"other_votes":498,"total_votes":36182,"dem_pct":43.22,"rep_pct":55.41},"45005":{"margin":9.8,"winner":"DEM","dem_votes":33582,"rep_votes":27410,"other_votes":1971,"total_votes":62963,"dem_pct":53.34,"rep_pct":43.53},"45007":{"margin":-2.44,"winner":"REP","dem_votes":24835,"rep_votes":26113,"other_votes":1479,"total_votes":52427,"dem_pct":47.37,"rep_pct":49.81},"45009":{"margin":2.72,"winner":"DEM","dem_votes":18805,"rep_votes":17778,"other_votes":1177,"total_votes":37760,"dem_pct":49.8,"rep_pct":47.08},"45011":{"margin":7.95,"winner":"DEM","dem_votes":32206,"rep_votes":27364,"other_votes":1337,"total_votes":60907,"dem_pct":52.88,"rep_pct":44.93},"45013":{"margin":-31.7,"winner":"REP","dem_votes":9100,"rep_votes":17818,"other_votes":582,"total_votes":27500,"dem_pct":33.09,"rep_pct":64.79},"45015":{"margin":5.63,"winner":"DEM","dem_votes":34548,"rep_votes":30772,"other_votes":1791,"total_votes":67111,"dem_pct":51.48,"rep_pct":45.85},"45017":{"margin":-13.56,"winner":"REP","dem_votes":19466,"rep_votes":25810,"other_votes":1499,"total_votes":46775,"dem_pct":41.62,"rep_pct":55.18},"45019":{"margin":15.42,"winner":"DEM","dem_votes":16752,"rep_votes":12226,"other_votes":371,"total_votes":29349,"dem_pct":57.08,"rep_pct":41.66},"45021":{"margin":3.64,"winner":"DEM","dem_votes":31159,"rep_votes":28911,"other_votes":1700,"total_votes":61770,"dem_pct":50.44,"rep_pct":46.8},"45023":{"margin":-16.76,"winner":"REP","dem_votes":7731,"rep_votes":10975,"other_votes":654,"total_votes":19360,"dem_pct":39.93,"rep_pct":56.69},"45025":{"margin":-14.31,"winner":"REP","dem_votes":16903,"rep_votes":22803,"other_votes":1510,"total_votes":41217,"dem_pct":41.01,"rep_pct":55.32},"45027":{"margin":12.81,"winner":"DEM","dem_votes":19950,"rep_votes":15321,"other_votes":865,"total_votes":36137,"dem_pct":55.21,"rep_pct":42.4},"45029":{"margin":-6.06,"winner":"REP","dem_votes":30653,"rep_votes":34665,"other_votes":892,"total_votes":66209,"dem_pct":46.3,"rep_pct":52.36},"45031":{"margin":-14.57,"winner":"REP","dem_votes":18978,"rep_votes":25594,"other_votes":828,"total_votes":45400,"dem_pct":41.8,"rep_pct":56.37},"45033":{"margin":-6.87,"winner":"REP","dem_votes":16688,"rep_votes":19193,"other_votes":560,"total_votes":36442,"dem_pct":45.79,"rep_pct":52.67},"45035":{"margin":-8.46,"winner":"REP","dem_votes":7459,"rep_votes":8873,"other_votes":387,"total_votes":16719,"dem_pct":44.61,"rep_pct":53.07},"45037":{"margin":-4.8,"winner":"REP","dem_votes":23085,"rep_votes":25471,"other_votes":1144,"total_votes":49699,"dem_pct":46.45,"rep_pct":51.25},"45039":{"margin":8.27,"winner":"DEM","dem_votes":11349,"rep_votes":9574,"other_votes":529,"total_votes":21452,"dem_pct":52.9,"rep_pct":44.63},"45041":{"margin":-0.3,"winner":"REP","dem_votes":17199,"rep_votes":17304,"other_votes":568,"total_votes":35070,"dem_pct":49.04,"rep_pct":49.34},"45043":{"margin":-17.77,"winner":"REP","dem_votes":16360,"rep_votes":23594,"other_votes":755,"total_votes":40709,"dem_pct":40.19,"rep_pct":57.96},"45045":{"margin":-13,"winner":"REP","dem_votes":16344,"rep_votes":21405,"other_votes":1194,"total_votes":38943,"dem_pct":41.97,"rep_pct":54.96},"45047":{"margin":-30.3,"winner":"REP","dem_votes":11953,"rep_votes":22706,"other_votes":833,"total_votes":35491,"dem_pct":33.68,"rep_pct":63.98},"45049":{"margin":-16.76,"winner":"REP","dem_votes":24785,"rep_votes":35040,"other_votes":1350,"total_votes":61175,"dem_pct":40.51,"rep_pct":57.28},"45051":{"margin":9,"winner":"DEM","dem_votes":14444,"rep_votes":12001,"other_votes":708,"total_votes":27154,"dem_pct":53.19,"rep_pct":44.2},"45053":{"margin":-31.47,"winner":"REP","dem_votes":13348,"rep_votes":26202,"other_votes":1294,"total_votes":40844,"dem_pct":32.68,"rep_pct":64.15},"45055":{"margin":1.82,"winner":"DEM","dem_votes":23566,"rep_votes":22693,"other_votes":1593,"total_votes":47852,"dem_pct":49.25,"rep_pct":47.42},"45057":{"margin":-23.6,"winner":"REP","dem_votes":9704,"rep_votes":15838,"other_votes":446,"total_votes":25988,"dem_pct":37.34,"rep_pct":60.94},"45059":{"margin":10.91,"winner":"DEM","dem_votes":25077,"rep_votes":20007,"other_votes":1394,"total_votes":46478,"dem_pct":53.95,"rep_pct":43.05},"45061":{"margin":-10.48,"winner":"REP","dem_votes":7405,"rep_votes":9209,"other_votes":605,"total_votes":17219,"dem_pct":43,"rep_pct":53.48},"45063":{"margin":-16.46,"winner":"REP","dem_votes":8991,"rep_votes":12623,"other_votes":450,"total_votes":22064,"dem_pct":40.75,"rep_pct":57.21},"45065":{"margin":16.65,"winner":"DEM","dem_votes":23091,"rep_votes":16282,"other_votes":1516,"total_votes":40888,"dem_pct":56.47,"rep_pct":39.82},"45067":{"margin":8.62,"winner":"DEM","dem_votes":22681,"rep_votes":19029,"other_votes":652,"total_votes":42362,"dem_pct":53.54,"rep_pct":44.92},"45069":{"margin":-22.84,"winner":"REP","dem_votes":20190,"rep_votes":32665,"other_votes":1764,"total_votes":54619,"dem_pct":36.97,"rep_pct":59.81},"45071":{"margin":-27.07,"winner":"REP","dem_votes":17171,"rep_votes":30430,"other_votes":1373,"total_votes":48973,"dem_pct":35.06,"rep_pct":62.14},"45073":{"margin":-13.97,"winner":"REP","dem_votes":22641,"rep_votes":30132,"other_votes":860,"total_votes":53633,"dem_pct":42.21,"rep_pct":56.18},"45075":{"margin":-0.49,"winner":"REP","dem_votes":13064,"rep_votes":13195,"other_votes":551,"total_votes":26810,"dem_pct":48.73,"rep_pct":49.22},"45077":{"margin":-11.55,"winner":"REP","dem_votes":6116,"rep_votes":7735,"other_votes":167,"total_votes":14017,"dem_pct":43.63,"rep_pct":55.18},"45079":{"margin":4.23,"winner":"DEM","dem_votes":12645,"rep_votes":11605,"other_votes":305,"total_votes":24555,"dem_pct":51.5,"rep_pct":47.26},"45081":{"margin":-13.29,"winner":"REP","dem_votes":24956,"rep_votes":32853,"other_votes":1623,"total_votes":59432,"dem_pct":41.99,"rep_pct":55.28},"45083":{"margin":-7.91,"winner":"REP","dem_votes":29362,"rep_votes":34604,"other_votes":2345,"total_votes":66311,"dem_pct":44.28,"rep_pct":52.19},"45085":{"margin":-1.85,"winner":"REP","dem_votes":17431,"rep_votes":18113,"other_votes":1298,"total_votes":36842,"dem_pct":47.31,"rep_pct":49.16},"45087":{"margin":-20.46,"winner":"REP","dem_votes":11927,"rep_votes":18159,"other_votes":378,"total_votes":30464,"dem_pct":39.15,"rep_pct":59.61},"45089":{"margin":3.05,"winner":"DEM","dem_votes":29197,"rep_votes":27437,"other_votes":1123,"total_votes":57757,"dem_pct":50.55,"rep_pct":47.51},"45091":{"margin":-19.48,"winner":"REP","dem_votes":23399,"rep_votes":34908,"other_votes":787,"total_votes":59094,"dem_pct":39.6,"rep_pct":59.07}}},"2000":{"candidates":{"dem":"Al Gore","rep":"George W. Bush"},"counties":{"45001":{"margin":-24.15,"winner":"REP","dem_votes":24127,"rep_votes":39720,"other_votes":721,"total_votes":64567,"dem_pct":37.37,"rep_pct":61.52},"45003":{"margin":-10.97,"winner":"REP","dem_votes":6482,"rep_votes":8147,"other_votes":542,"total_votes":15171,"dem_pct":42.73,"rep_pct":53.7},"45005":{"margin":-1.94,"winner":"REP","dem_votes":30662,"rep_votes":31899,"other_votes":1197,"total_votes":63758,"dem_pct":48.09,"rep_pct":50.03},"45007":{"margin":-14.06,"winner":"REP","dem_votes":13700,"rep_votes":18252,"other_votes":417,"total_votes":32369,"dem_pct":42.32,"rep_pct":56.39},"45009":{"margin":-28.93,"winner":"REP","dem_votes":16360,"rep_votes":30340,"other_votes":1620,"total_votes":48320,"dem_pct":33.86,"rep_pct":62.79},"45011":{"margin":-21.69,"winner":"REP","dem_votes":7712,"rep_votes":12149,"other_votes":594,"total_votes":20455,"dem_pct":37.7,"rep_pct":59.39},"45013":{"margin":-23.78,"winner":"REP","dem_votes":12644,"rep_votes":20680,"other_votes":464,"total_votes":33788,"dem_pct":37.42,"rep_pct":61.2},"45015":{"margin":-41.31,"winner":"REP","dem_votes":15684,"rep_votes":38593,"other_votes":1181,"total_votes":55458,"dem_pct":28.28,"rep_pct":69.59},"45017":{"margin":-4.06,"winner":"REP","dem_votes":31149,"rep_votes":33832,"other_votes":1114,"total_votes":66095,"dem_pct":47.13,"rep_pct":51.19},"45019":{"margin":-31.96,"winner":"REP","dem_votes":19240,"rep_votes":37885,"other_votes":1205,"total_votes":58331,"dem_pct":32.98,"rep_pct":64.95},"45021":{"margin":-14.03,"winner":"REP","dem_votes":13632,"rep_votes":18223,"other_votes":867,"total_votes":32722,"dem_pct":41.66,"rep_pct":55.69},"45023":{"margin":-35.37,"winner":"REP","dem_votes":15249,"rep_votes":32629,"other_votes":1256,"total_votes":49133,"dem_pct":31.04,"rep_pct":66.41},"45025":{"margin":-10.54,"winner":"REP","dem_votes":23434,"rep_votes":29210,"other_votes":2173,"total_votes":54817,"dem_pct":42.75,"rep_pct":53.29},"45027":{"margin":-20.64,"winner":"REP","dem_votes":26981,"rep_votes":41380,"other_votes":1390,"total_votes":69751,"dem_pct":38.68,"rep_pct":59.33},"45029":{"margin":-12.29,"winner":"REP","dem_votes":5809,"rep_votes":7472,"other_votes":250,"total_votes":13530,"dem_pct":42.93,"rep_pct":55.22},"45031":{"margin":-37.48,"winner":"REP","dem_votes":19595,"rep_votes":44513,"other_votes":2375,"total_votes":66483,"dem_pct":29.47,"rep_pct":66.95},"45033":{"margin":-35.63,"winner":"REP","dem_votes":8241,"rep_votes":17587,"other_votes":403,"total_votes":26231,"dem_pct":31.42,"rep_pct":67.05},"45035":{"margin":-25.43,"winner":"REP","dem_votes":16316,"rep_votes":27729,"other_votes":841,"total_votes":44885,"dem_pct":36.35,"rep_pct":61.78},"45037":{"margin":-1.38,"winner":"REP","dem_votes":28042,"rep_votes":28857,"other_votes":2312,"total_votes":59211,"dem_pct":47.36,"rep_pct":48.74},"45039":{"margin":-11.67,"winner":"REP","dem_votes":15649,"rep_votes":19970,"other_votes":1407,"total_votes":37026,"dem_pct":42.26,"rep_pct":53.93},"45041":{"margin":-26.98,"winner":"REP","dem_votes":5062,"rep_votes":8987,"other_votes":494,"total_votes":14543,"dem_pct":34.81,"rep_pct":61.79},"45043":{"margin":7.48,"winner":"DEM","dem_votes":24223,"rep_votes":20734,"other_votes":1662,"total_votes":46619,"dem_pct":51.96,"rep_pct":44.48},"45045":{"margin":3.46,"winner":"DEM","dem_votes":34583,"rep_votes":32242,"other_votes":819,"total_votes":67644,"dem_pct":51.12,"rep_pct":47.66},"45047":{"margin":12.37,"winner":"DEM","dem_votes":32295,"rep_votes":25081,"other_votes":919,"total_votes":58296,"dem_pct":55.4,"rep_pct":43.02},"45049":{"margin":-2.26,"winner":"REP","dem_votes":18115,"rep_votes":18968,"other_votes":665,"total_votes":37748,"dem_pct":47.99,"rep_pct":50.25},"45051":{"margin":-14.61,"winner":"REP","dem_votes":29118,"rep_votes":39528,"other_votes":2612,"total_votes":71258,"dem_pct":40.86,"rep_pct":55.47},"45053":{"margin":-30.93,"winner":"REP","dem_votes":10235,"rep_votes":19704,"other_votes":675,"total_votes":30614,"dem_pct":33.43,"rep_pct":64.36},"45055":{"margin":-22.7,"winner":"REP","dem_votes":8463,"rep_votes":13694,"other_votes":891,"total_votes":23048,"dem_pct":36.72,"rep_pct":59.42},"45057":{"margin":-10.48,"winner":"REP","dem_votes":7626,"rep_votes":9454,"other_votes":367,"total_votes":17447,"dem_pct":43.71,"rep_pct":54.19},"45059":{"margin":-22.39,"winner":"REP","dem_votes":17182,"rep_votes":27454,"other_votes":1244,"total_votes":45880,"dem_pct":37.45,"rep_pct":59.84},"45061":{"margin":-17.79,"winner":"REP","dem_votes":9395,"rep_votes":13657,"other_votes":909,"total_votes":23961,"dem_pct":39.21,"rep_pct":57},"45063":{"margin":-21.56,"winner":"REP","dem_votes":26075,"rep_votes":40671,"other_votes":958,"total_votes":67704,"dem_pct":38.51,"rep_pct":60.07},"45065":{"margin":-3.64,"winner":"REP","dem_votes":13944,"rep_votes":15033,"other_votes":983,"total_votes":29960,"dem_pct":46.54,"rep_pct":50.18},"45067":{"margin":-39.45,"winner":"REP","dem_votes":4706,"rep_votes":11131,"other_votes":450,"total_votes":16287,"dem_pct":28.89,"rep_pct":68.35},"45069":{"margin":-28.6,"winner":"REP","dem_votes":18933,"rep_votes":34539,"other_votes":1086,"total_votes":54559,"dem_pct":34.7,"rep_pct":63.31},"45071":{"margin":-26.18,"winner":"REP","dem_votes":20184,"rep_votes":35123,"other_votes":1748,"total_votes":57055,"dem_pct":35.38,"rep_pct":61.56},"45073":{"margin":-31.34,"winner":"REP","dem_votes":15954,"rep_votes":31357,"other_votes":1842,"total_votes":49153,"dem_pct":32.46,"rep_pct":63.8},"45075":{"margin":-25.41,"winner":"REP","dem_votes":18641,"rep_votes":31715,"other_votes":1106,"total_votes":51462,"dem_pct":36.22,"rep_pct":61.63},"45077":{"margin":-38.15,"winner":"REP","dem_votes":16099,"rep_votes":36650,"other_votes":1125,"total_votes":53874,"dem_pct":29.88,"rep_pct":68.03},"45079":{"margin":-12.26,"winner":"REP","dem_votes":10473,"rep_votes":13491,"other_votes":654,"total_votes":24619,"dem_pct":42.54,"rep_pct":54.8},"45081":{"margin":-12.77,"winner":"REP","dem_votes":28565,"rep_votes":37124,"other_votes":1332,"total_votes":67021,"dem_pct":42.62,"rep_pct":55.39},"45083":{"margin":-9.35,"winner":"REP","dem_votes":30066,"rep_votes":36401,"other_votes":1295,"total_votes":67763,"dem_pct":44.37,"rep_pct":53.72},"45085":{"margin":-0.41,"winner":"REP","dem_votes":29085,"rep_votes":29332,"other_votes":1271,"total_votes":59687,"dem_pct":48.73,"rep_pct":49.14},"45087":{"margin":-16.11,"winner":"REP","dem_votes":24243,"rep_votes":33988,"other_votes":2238,"total_votes":60469,"dem_pct":40.09,"rep_pct":56.21},"45089":{"margin":7.84,"winner":"DEM","dem_votes":28053,"rep_votes":23863,"other_votes":1560,"total_votes":53476,"dem_pct":52.46,"rep_pct":44.62},"45091":{"margin":-18.71,"winner":"REP","dem_votes":27664,"rep_votes":40962,"other_votes":2465,"total_votes":71091,"dem_pct":38.91,"rep_pct":57.62}}},"2004":{"candidates":{"dem":"John Kerry","rep":"George W. Bush"},"counties":{"45001":{"margin":-28.04,"winner":"REP","dem_votes":12362,"rep_votes":22411,"other_votes":1063,"total_votes":35836,"dem_pct":34.49,"rep_pct":62.54},"45003":{"margin":-38.39,"winner":"REP","dem_votes":15639,"rep_votes":35540,"other_votes":660,"total_votes":51839,"dem_pct":30.17,"rep_pct":68.56},"45005":{"margin":-16.27,"winner":"REP","dem_votes":15439,"rep_votes":21546,"other_votes":544,"total_votes":37529,"dem_pct":41.14,"rep_pct":57.41},"45007":{"margin":-9.94,"winner":"REP","dem_votes":11752,"rep_votes":14439,"other_votes":837,"total_votes":27028,"dem_pct":43.48,"rep_pct":53.42},"45009":{"margin":-21.36,"winner":"REP","dem_votes":6377,"rep_votes":10011,"other_votes":623,"total_votes":17011,"dem_pct":37.49,"rep_pct":58.85},"45011":{"margin":-16.2,"winner":"REP","dem_votes":19574,"rep_votes":27308,"other_votes":873,"total_votes":47755,"dem_pct":40.99,"rep_pct":57.18},"45013":{"margin":-17.98,"winner":"REP","dem_votes":27203,"rep_votes":39613,"other_votes":2222,"total_votes":69037,"dem_pct":39.4,"rep_pct":57.38},"45015":{"margin":-17.01,"winner":"REP","dem_votes":10648,"rep_votes":15093,"other_votes":393,"total_votes":26134,"dem_pct":40.74,"rep_pct":57.75},"45017":{"margin":-31.03,"winner":"REP","dem_votes":16255,"rep_votes":31537,"other_votes":1453,"total_votes":49245,"dem_pct":33.01,"rep_pct":64.04},"45019":{"margin":-0.93,"winner":"REP","dem_votes":10026,"rep_votes":10215,"other_votes":216,"total_votes":20457,"dem_pct":49.01,"rep_pct":49.94},"45021":{"margin":-19.25,"winner":"REP","dem_votes":23052,"rep_votes":34303,"other_votes":1100,"total_votes":58455,"dem_pct":39.44,"rep_pct":58.68},"45023":{"margin":-15.83,"winner":"REP","dem_votes":11038,"rep_votes":15270,"other_votes":419,"total_votes":26727,"dem_pct":41.3,"rep_pct":57.13},"45025":{"margin":-37.96,"winner":"REP","dem_votes":15985,"rep_votes":36893,"other_votes":2195,"total_votes":55073,"dem_pct":29.03,"rep_pct":66.99},"45027":{"margin":-28.37,"winner":"REP","dem_votes":21022,"rep_votes":38562,"other_votes":2238,"total_votes":61822,"dem_pct":34,"rep_pct":62.38},"45029":{"margin":-4.59,"winner":"REP","dem_votes":24456,"rep_votes":26857,"other_votes":970,"total_votes":52284,"dem_pct":46.78,"rep_pct":51.37},"45031":{"margin":-12.75,"winner":"REP","dem_votes":25520,"rep_votes":33085,"other_votes":729,"total_votes":59334,"dem_pct":43.01,"rep_pct":55.76},"45033":{"margin":-25.25,"winner":"REP","dem_votes":9699,"rep_votes":16484,"other_votes":690,"total_votes":26873,"dem_pct":36.09,"rep_pct":61.34},"45035":{"margin":9.71,"winner":"DEM","dem_votes":29097,"rep_votes":23853,"other_votes":1080,"total_votes":54030,"dem_pct":53.85,"rep_pct":44.15},"45037":{"margin":4.49,"winner":"DEM","dem_votes":7185,"rep_votes":6558,"other_votes":206,"total_votes":13949,"dem_pct":51.51,"rep_pct":47.02},"45039":{"margin":-23.4,"winner":"REP","dem_votes":24198,"rep_votes":39357,"other_votes":1236,"total_votes":64791,"dem_pct":37.35,"rep_pct":60.74},"45041":{"margin":-14.88,"winner":"REP","dem_votes":29750,"rep_votes":40608,"other_votes":2616,"total_votes":72974,"dem_pct":40.77,"rep_pct":55.65},"45043":{"margin":-3.37,"winner":"REP","dem_votes":7807,"rep_votes":8371,"other_votes":575,"total_votes":16753,"dem_pct":46.6,"rep_pct":49.97},"45045":{"margin":-42.97,"winner":"REP","dem_votes":17177,"rep_votes":44944,"other_votes":2493,"total_votes":64614,"dem_pct":26.58,"rep_pct":69.56},"45047":{"margin":-20.39,"winner":"REP","dem_votes":11614,"rep_votes":17843,"other_votes":1081,"total_votes":30538,"dem_pct":38.03,"rep_pct":58.43},"45049":{"margin":-28.9,"winner":"REP","dem_votes":13686,"rep_votes":25246,"other_votes":1070,"total_votes":40002,"dem_pct":34.21,"rep_pct":63.11},"45051":{"margin":-22.46,"winner":"REP","dem_votes":10729,"rep_votes":17069,"other_votes":428,"total_votes":28226,"dem_pct":38.01,"rep_pct":60.47},"45053":{"margin":-40.34,"winner":"REP","dem_votes":18230,"rep_votes":43409,"other_votes":777,"total_votes":62416,"dem_pct":29.21,"rep_pct":69.55},"45055":{"margin":-15.51,"winner":"REP","dem_votes":16278,"rep_votes":22444,"other_votes":1023,"total_votes":39745,"dem_pct":40.96,"rep_pct":56.47},"45057":{"margin":-19.42,"winner":"REP","dem_votes":16450,"rep_votes":24756,"other_votes":1558,"total_votes":42764,"dem_pct":38.47,"rep_pct":57.89},"45059":{"margin":-15.34,"winner":"REP","dem_votes":6050,"rep_votes":8312,"other_votes":378,"total_votes":14740,"dem_pct":41.04,"rep_pct":56.39},"45061":{"margin":-36.15,"winner":"REP","dem_votes":21356,"rep_votes":45984,"other_votes":784,"total_votes":68124,"dem_pct":31.35,"rep_pct":67.5},"45063":{"margin":-22.07,"winner":"REP","dem_votes":23217,"rep_votes":36828,"other_votes":1622,"total_votes":61666,"dem_pct":37.65,"rep_pct":59.72},"45065":{"margin":-32.77,"winner":"REP","dem_votes":12910,"rep_votes":25760,"other_votes":540,"total_votes":39210,"dem_pct":32.93,"rep_pct":65.7},"45067":{"margin":-16.73,"winner":"REP","dem_votes":19388,"rep_votes":27440,"other_votes":1314,"total_votes":48141,"dem_pct":40.27,"rep_pct":57},"45069":{"margin":-3.22,"winner":"REP","dem_votes":7665,"rep_votes":8188,"other_votes":366,"total_votes":16219,"dem_pct":47.26,"rep_pct":50.48},"45071":{"margin":-1.19,"winner":"REP","dem_votes":30247,"rep_votes":30990,"other_votes":1135,"total_votes":62372,"dem_pct":48.49,"rep_pct":49.69},"45073":{"margin":-12.14,"winner":"REP","dem_votes":8948,"rep_votes":11491,"other_votes":514,"total_votes":20953,"dem_pct":42.71,"rep_pct":54.84},"45075":{"margin":-15.08,"winner":"REP","dem_votes":10416,"rep_votes":14296,"other_votes":1023,"total_votes":25734,"dem_pct":40.47,"rep_pct":55.55},"45077":{"margin":-15.38,"winner":"REP","dem_votes":22847,"rep_votes":31427,"other_votes":1514,"total_votes":55788,"dem_pct":40.95,"rep_pct":56.33},"45079":{"margin":-26.57,"winner":"REP","dem_votes":20559,"rep_votes":36265,"other_votes":2281,"total_votes":59104,"dem_pct":34.78,"rep_pct":61.36},"45081":{"margin":-15.48,"winner":"REP","dem_votes":6736,"rep_votes":9296,"other_votes":501,"total_votes":16534,"dem_pct":40.74,"rep_pct":56.23},"45083":{"margin":-29.78,"winner":"REP","dem_votes":24410,"rep_votes":45895,"other_votes":1849,"total_votes":72154,"dem_pct":33.83,"rep_pct":63.61},"45085":{"margin":-27.13,"winner":"REP","dem_votes":20371,"rep_votes":36284,"other_votes":2001,"total_votes":58656,"dem_pct":34.73,"rep_pct":61.86},"45087":{"margin":-16.1,"winner":"REP","dem_votes":28794,"rep_votes":39992,"other_votes":750,"total_votes":69536,"dem_pct":41.41,"rep_pct":57.51},"45089":{"margin":-16.5,"winner":"REP","dem_votes":29898,"rep_votes":42145,"other_votes":2170,"total_votes":74212,"dem_pct":40.29,"rep_pct":56.79},"45091":{"margin":-8.63,"winner":"REP","dem_votes":16457,"rep_votes":19704,"other_votes":1439,"total_votes":37600,"dem_pct":43.77,"rep_pct":52.4}}},"2008":{"candidates":{"dem":"Barack Obama","rep":"John McCain"},"counties":{"45001":{"margin":-15.19,"winner":"REP","dem_votes":4593,"rep_votes":6264,"other_votes":144,"total_votes":11001,"dem_pct":41.75,"rep_pct":56.94},"45003":{"margin":-24,"winner":"REP","dem_votes":26101,"rep_votes":42849,"other_votes":820,"total_votes":69770,"dem_pct":37.41,"rep_pct":61.41},"45005":{"margin":51.74,"winner":"DEM","dem_votes":3029,"rep_votes":947,"other_votes":48,"total_votes":4024,"dem_pct":75.27,"rep_pct":23.53},"45007":{"margin":-33.29,"winner":"REP","dem_votes":24132,"rep_votes":48690,"other_votes":965,"total_votes":73787,"dem_pct":32.7,"rep_pct":65.99},"45009":{"margin":31.06,"winner":"DEM","dem_votes":4426,"rep_votes":2309,"other_votes":79,"total_votes":6814,"dem_pct":64.95,"rep_pct":33.89},"45011":{"margin":1.66,"winner":"DEM","dem_votes":4931,"rep_votes":4769,"other_votes":98,"total_votes":9798,"dem_pct":50.33,"rep_pct":48.67},"45013":{"margin":-10.78,"winner":"REP","dem_votes":30396,"rep_votes":37821,"other_votes":653,"total_votes":68870,"dem_pct":44.14,"rep_pct":54.92},"45015":{"margin":-13.05,"winner":"REP","dem_votes":27755,"rep_votes":36205,"other_votes":821,"total_votes":64781,"dem_pct":42.84,"rep_pct":55.89},"45017":{"margin":3.56,"winner":"DEM","dem_votes":3970,"rep_votes":3695,"other_votes":73,"total_votes":7738,"dem_pct":51.31,"rep_pct":47.75},"45019":{"margin":8.34,"winner":"DEM","dem_votes":82698,"rep_votes":69822,"other_votes":1914,"total_votes":154434,"dem_pct":53.55,"rep_pct":45.21},"45021":{"margin":-29.33,"winner":"REP","dem_votes":7215,"rep_votes":13305,"other_votes":246,"total_votes":20766,"dem_pct":34.74,"rep_pct":64.07},"45023":{"margin":8.3,"winner":"DEM","dem_votes":7478,"rep_votes":6318,"other_votes":185,"total_votes":13981,"dem_pct":53.49,"rep_pct":45.19},"45025":{"margin":-2.95,"winner":"REP","dem_votes":7842,"rep_votes":8325,"other_votes":192,"total_votes":16359,"dem_pct":47.94,"rep_pct":50.89},"45027":{"margin":12.32,"winner":"DEM","dem_votes":8673,"rep_votes":6758,"other_votes":121,"total_votes":15552,"dem_pct":55.77,"rep_pct":43.45},"45029":{"margin":0.52,"winner":"DEM","dem_votes":8616,"rep_votes":8525,"other_votes":180,"total_votes":17321,"dem_pct":49.74,"rep_pct":49.22},"45031":{"margin":-0.13,"winner":"REP","dem_votes":14505,"rep_votes":14544,"other_votes":285,"total_votes":29334,"dem_pct":49.45,"rep_pct":49.58},"45033":{"margin":11.43,"winner":"DEM","dem_votes":7408,"rep_votes":5874,"other_votes":135,"total_votes":13417,"dem_pct":55.21,"rep_pct":43.78},"45035":{"margin":-15.5,"winner":"REP","dem_votes":21806,"rep_votes":29929,"other_votes":670,"total_votes":52405,"dem_pct":41.61,"rep_pct":57.11},"45037":{"margin":-10.93,"winner":"REP","dem_votes":5075,"rep_votes":6334,"other_votes":111,"total_votes":11520,"dem_pct":44.05,"rep_pct":54.98},"45039":{"margin":31.66,"winner":"DEM","dem_votes":7591,"rep_votes":3912,"other_votes":116,"total_votes":11619,"dem_pct":65.33,"rep_pct":33.67},"45041":{"margin":-3.17,"winner":"REP","dem_votes":28012,"rep_votes":29861,"other_votes":500,"total_votes":58373,"dem_pct":47.99,"rep_pct":51.16},"45043":{"margin":-5.25,"winner":"REP","dem_votes":14199,"rep_votes":15790,"other_votes":301,"total_votes":30290,"dem_pct":46.88,"rep_pct":52.13},"45045":{"margin":-23.85,"winner":"REP","dem_votes":70886,"rep_votes":116363,"other_votes":3408,"total_votes":190657,"dem_pct":37.18,"rep_pct":61.03},"45047":{"margin":-15.67,"winner":"REP","dem_votes":12348,"rep_votes":16995,"other_votes":324,"total_votes":29667,"dem_pct":41.62,"rep_pct":57.29},"45049":{"margin":25.42,"winner":"DEM","dem_votes":5816,"rep_votes":3439,"other_votes":95,"total_votes":9350,"dem_pct":62.2,"rep_pct":36.78},"45051":{"margin":-24.55,"winner":"REP","dem_votes":38879,"rep_votes":64609,"other_votes":1310,"total_votes":104798,"dem_pct":37.1,"rep_pct":61.65},"45053":{"margin":22.86,"winner":"DEM","dem_votes":5389,"rep_votes":3365,"other_votes":100,"total_votes":8854,"dem_pct":60.87,"rep_pct":38.01},"45055":{"margin":-18.73,"winner":"REP","dem_votes":11226,"rep_votes":16466,"other_votes":293,"total_votes":27985,"dem_pct":40.11,"rep_pct":58.84},"45057":{"margin":-14.88,"winner":"REP","dem_votes":12139,"rep_votes":16441,"other_votes":341,"total_votes":28921,"dem_pct":41.97,"rep_pct":56.85},"45059":{"margin":-18.09,"winner":"REP","dem_votes":10578,"rep_votes":15334,"other_votes":370,"total_votes":26282,"dem_pct":40.25,"rep_pct":58.34},"45061":{"margin":31.54,"winner":"DEM","dem_votes":5960,"rep_votes":3074,"other_votes":119,"total_votes":9153,"dem_pct":65.12,"rep_pct":33.58},"45063":{"margin":-38.04,"winner":"REP","dem_votes":33303,"rep_votes":74960,"other_votes":1249,"total_votes":109512,"dem_pct":30.41,"rep_pct":68.45},"45065":{"margin":27.63,"winner":"DEM","dem_votes":9608,"rep_votes":5416,"other_votes":150,"total_votes":15174,"dem_pct":63.32,"rep_pct":35.69},"45067":{"margin":25.73,"winner":"DEM","dem_votes":6794,"rep_votes":3996,"other_votes":86,"total_votes":10876,"dem_pct":62.47,"rep_pct":36.74},"45069":{"margin":6.08,"winner":"DEM","dem_votes":2755,"rep_votes":2437,"other_votes":40,"total_votes":5232,"dem_pct":52.66,"rep_pct":46.58},"45071":{"margin":-17.59,"winner":"REP","dem_votes":6708,"rep_votes":9616,"other_votes":200,"total_votes":16524,"dem_pct":40.6,"rep_pct":58.19},"45073":{"margin":-37.53,"winner":"REP","dem_votes":9481,"rep_votes":21164,"other_votes":487,"total_votes":31132,"dem_pct":30.45,"rep_pct":67.98},"45075":{"margin":38.11,"winner":"DEM","dem_votes":27263,"rep_votes":12115,"other_votes":376,"total_votes":39754,"dem_pct":68.58,"rep_pct":30.47},"45077":{"margin":-46.22,"winner":"REP","dem_votes":11691,"rep_votes":32552,"other_votes":885,"total_votes":45128,"dem_pct":25.91,"rep_pct":72.13},"45079":{"margin":28.91,"winner":"DEM","dem_votes":105656,"rep_votes":57941,"other_votes":1440,"total_votes":165037,"dem_pct":64.02,"rep_pct":35.11},"45081":{"margin":-21.71,"winner":"REP","dem_votes":3323,"rep_votes":5191,"other_votes":89,"total_votes":8603,"dem_pct":38.63,"rep_pct":60.34},"45083":{"margin":-21.61,"winner":"REP","dem_votes":41632,"rep_votes":65042,"other_votes":1654,"total_votes":108328,"dem_pct":38.43,"rep_pct":60.04},"45085":{"margin":15.44,"winner":"DEM","dem_votes":25431,"rep_votes":18581,"other_votes":346,"total_votes":44358,"dem_pct":57.33,"rep_pct":41.89},"45087":{"margin":-11.17,"winner":"REP","dem_votes":5935,"rep_votes":7449,"other_votes":167,"total_votes":13551,"dem_pct":43.8,"rep_pct":54.97},"45089":{"margin":38.16,"winner":"DEM","dem_votes":11279,"rep_votes":5004,"other_votes":160,"total_votes":16443,"dem_pct":68.59,"rep_pct":30.43},"45091":{"margin":-17.7,"winner":"REP","dem_votes":37918,"rep_votes":54500,"other_votes":1278,"total_votes":93696,"dem_pct":40.47,"rep_pct":58.17}}},"2012":{"candidates":{"dem":"Barack Obama","rep":"Mitt Romney"},"counties":{"45001":{"margin":-13.39,"winner":"REP","dem_votes":4507,"rep_votes":5923,"other_votes":147,"total_votes":10577,"dem_pct":42.61,"rep_pct":56},"45003":{"margin":-26.04,"winner":"REP","dem_votes":23953,"rep_votes":41157,"other_votes":939,"total_votes":66049,"dem_pct":36.27,"rep_pct":62.31},"45005":{"margin":57.34,"winner":"DEM","dem_votes":3335,"rep_votes":894,"other_votes":28,"total_votes":4257,"dem_pct":78.34,"rep_pct":21},"45007":{"margin":-36.4,"winner":"REP","dem_votes":22315,"rep_votes":48493,"other_votes":1093,"total_votes":71901,"dem_pct":31.04,"rep_pct":67.44},"45009":{"margin":35.16,"winner":"DEM","dem_votes":4600,"rep_votes":2190,"other_votes":64,"total_votes":6854,"dem_pct":67.11,"rep_pct":31.95},"45011":{"margin":5.31,"winner":"DEM","dem_votes":5182,"rep_votes":4655,"other_votes":76,"total_votes":9913,"dem_pct":52.27,"rep_pct":46.96},"45013":{"margin":-17.52,"winner":"REP","dem_votes":29775,"rep_votes":42580,"other_votes":760,"total_votes":73115,"dem_pct":40.72,"rep_pct":58.24},"45015":{"margin":-18.86,"winner":"REP","dem_votes":24239,"rep_votes":35764,"other_votes":1108,"total_votes":61111,"dem_pct":39.66,"rep_pct":58.52},"45017":{"margin":4.31,"winner":"DEM","dem_votes":4043,"rep_votes":3705,"other_votes":82,"total_votes":7830,"dem_pct":51.63,"rep_pct":47.32},"45019":{"margin":2.35,"winner":"DEM","dem_votes":81027,"rep_votes":77248,"other_votes":2579,"total_votes":160854,"dem_pct":50.37,"rep_pct":48.02},"45021":{"margin":-29.33,"winner":"REP","dem_votes":7219,"rep_votes":13306,"other_votes":228,"total_votes":20753,"dem_pct":34.79,"rep_pct":64.12},"45023":{"margin":10.5,"winner":"DEM","dem_votes":7839,"rep_votes":6336,"other_votes":149,"total_votes":14324,"dem_pct":54.73,"rep_pct":44.23},"45025":{"margin":-3.3,"winner":"REP","dem_votes":7942,"rep_votes":8488,"other_votes":146,"total_votes":16576,"dem_pct":47.91,"rep_pct":51.21},"45027":{"margin":13,"winner":"DEM","dem_votes":8967,"rep_votes":6890,"other_votes":128,"total_votes":15985,"dem_pct":56.1,"rep_pct":43.1},"45029":{"margin":0.18,"winner":"DEM","dem_votes":8470,"rep_votes":8439,"other_votes":168,"total_votes":17077,"dem_pct":49.6,"rep_pct":49.42},"45031":{"margin":3.4,"winner":"DEM","dem_votes":15452,"rep_votes":14429,"other_votes":259,"total_votes":30140,"dem_pct":51.27,"rep_pct":47.87},"45033":{"margin":16.27,"winner":"DEM","dem_votes":7623,"rep_votes":5477,"other_votes":86,"total_votes":13186,"dem_pct":57.81,"rep_pct":41.54},"45035":{"margin":-16,"winner":"REP","dem_votes":23390,"rep_votes":32469,"other_votes":876,"total_votes":56735,"dem_pct":41.23,"rep_pct":57.23},"45037":{"margin":-13.35,"winner":"REP","dem_votes":4965,"rep_votes":6511,"other_votes":107,"total_votes":11583,"dem_pct":42.86,"rep_pct":56.21},"45039":{"margin":31.6,"winner":"DEM","dem_votes":7743,"rep_votes":3996,"other_votes":119,"total_votes":11858,"dem_pct":65.3,"rep_pct":33.7},"45041":{"margin":-0.54,"winner":"REP","dem_votes":28508,"rep_votes":28825,"other_votes":544,"total_votes":57877,"dem_pct":49.26,"rep_pct":49.8},"45043":{"margin":-7.63,"winner":"REP","dem_votes":14119,"rep_votes":16476,"other_votes":275,"total_votes":30870,"dem_pct":45.74,"rep_pct":53.37},"45045":{"margin":-27.78,"winner":"REP","dem_votes":67378,"rep_votes":120514,"other_votes":3390,"total_votes":191282,"dem_pct":35.22,"rep_pct":63},"45047":{"margin":-15.45,"winner":"REP","dem_votes":11884,"rep_votes":16290,"other_votes":351,"total_votes":28525,"dem_pct":41.66,"rep_pct":57.11},"45049":{"margin":27.27,"winner":"DEM","dem_votes":5814,"rep_votes":3310,"other_votes":60,"total_votes":9184,"dem_pct":63.31,"rep_pct":36.04},"45051":{"margin":-28.72,"winner":"REP","dem_votes":36620,"rep_votes":66653,"other_votes":1311,"total_votes":104584,"dem_pct":35.01,"rep_pct":63.73},"45053":{"margin":15.59,"winner":"DEM","dem_votes":5727,"rep_votes":4169,"other_votes":95,"total_votes":9991,"dem_pct":57.32,"rep_pct":41.73},"45055":{"margin":-18.59,"winner":"REP","dem_votes":10821,"rep_votes":15846,"other_votes":359,"total_votes":27026,"dem_pct":40.04,"rep_pct":58.63},"45057":{"margin":-17.96,"winner":"REP","dem_votes":13345,"rep_votes":19273,"other_votes":392,"total_votes":33010,"dem_pct":40.43,"rep_pct":58.39},"45059":{"margin":-17.46,"winner":"REP","dem_votes":10297,"rep_votes":14726,"other_votes":350,"total_votes":25373,"dem_pct":40.58,"rep_pct":58.04},"45061":{"margin":35.33,"winner":"DEM","dem_votes":5972,"rep_votes":2829,"other_votes":97,"total_votes":8898,"dem_pct":67.12,"rep_pct":31.79},"45063":{"margin":-37.77,"winner":"REP","dem_votes":34007,"rep_votes":76392,"other_votes":1805,"total_votes":112204,"dem_pct":30.31,"rep_pct":68.08},"45065":{"margin":3.44,"winner":"DEM","dem_votes":2637,"rep_votes":2460,"other_votes":40,"total_votes":5137,"dem_pct":51.33,"rep_pct":47.89},"45067":{"margin":29.83,"winner":"DEM","dem_votes":9518,"rep_votes":5114,"other_votes":134,"total_votes":14766,"dem_pct":64.46,"rep_pct":34.63},"45069":{"margin":30.4,"winner":"DEM","dem_votes":7554,"rep_votes":4010,"other_votes":93,"total_votes":11657,"dem_pct":64.8,"rep_pct":34.4},"45071":{"margin":-14.29,"winner":"REP","dem_votes":6891,"rep_votes":9218,"other_votes":178,"total_votes":16287,"dem_pct":42.31,"rep_pct":56.6},"45073":{"margin":-42.58,"winner":"REP","dem_votes":8537,"rep_votes":21573,"other_votes":503,"total_votes":30613,"dem_pct":27.89,"rep_pct":70.47},"45075":{"margin":43.55,"winner":"DEM","dem_votes":30454,"rep_votes":11888,"other_votes":295,"total_votes":42637,"dem_pct":71.43,"rep_pct":27.88},"45077":{"margin":-49.01,"winner":"REP","dem_votes":11122,"rep_votes":33385,"other_votes":915,"total_votes":45422,"dem_pct":24.49,"rep_pct":73.5},"45079":{"margin":33.3,"winner":"DEM","dem_votes":94350,"rep_votes":46725,"other_votes":1941,"total_votes":143016,"dem_pct":65.97,"rep_pct":32.67},"45081":{"margin":-21.14,"winner":"REP","dem_votes":3322,"rep_votes":5130,"other_votes":101,"total_votes":8553,"dem_pct":38.84,"rep_pct":59.98},"45083":{"margin":-23.11,"winner":"REP","dem_votes":40920,"rep_votes":65951,"other_votes":1456,"total_votes":108327,"dem_pct":37.77,"rep_pct":60.88},"45085":{"margin":17.52,"winner":"DEM","dem_votes":27550,"rep_votes":19266,"other_votes":445,"total_votes":47261,"dem_pct":58.29,"rep_pct":40.77},"45087":{"margin":-6.55,"winner":"REP","dem_votes":5748,"rep_votes":6566,"other_votes":161,"total_votes":12475,"dem_pct":46.08,"rep_pct":52.63},"45089":{"margin":39.91,"winner":"DEM","dem_votes":11318,"rep_votes":4819,"other_votes":145,"total_votes":16282,"dem_pct":69.51,"rep_pct":29.6},"45091":{"margin":-20.51,"winner":"REP","dem_votes":38757,"rep_votes":59149,"other_votes":1522,"total_votes":99428,"dem_pct":38.98,"rep_pct":59.49}}},"2016":{"candidates":{"dem":"Hillary Clinton","rep":"Donald Trump"},"counties":{"45001":{"margin":-28.26,"winner":"REP","dem_votes":3712,"rep_votes":6742,"other_votes":270,"total_votes":10724,"dem_pct":34.61,"rep_pct":62.87},"45003":{"margin":-27.49,"winner":"REP","dem_votes":25426,"rep_votes":45981,"other_votes":3366,"total_votes":74773,"dem_pct":34,"rep_pct":61.49},"45005":{"margin":54.06,"winner":"DEM","dem_votes":2722,"rep_votes":788,"other_votes":68,"total_votes":3578,"dem_pct":76.08,"rep_pct":22.02},"45007":{"margin":-43.68,"winner":"REP","dem_votes":21040,"rep_votes":56109,"other_votes":3147,"total_votes":80296,"dem_pct":26.2,"rep_pct":69.88},"45009":{"margin":27.27,"winner":"DEM","dem_votes":3886,"rep_votes":2197,"other_votes":112,"total_votes":6195,"dem_pct":62.73,"rep_pct":35.46},"45011":{"margin":-5.2,"winner":"REP","dem_votes":4395,"rep_votes":4888,"other_votes":196,"total_votes":9479,"dem_pct":46.37,"rep_pct":51.57},"45013":{"margin":-14.31,"winner":"REP","dem_votes":29577,"rep_votes":39986,"other_votes":3207,"total_votes":72770,"dem_pct":40.64,"rep_pct":54.95},"45015":{"margin":-17.4,"winner":"REP","dem_votes":30492,"rep_votes":44223,"other_votes":4204,"total_votes":78919,"dem_pct":38.64,"rep_pct":56.04},"45017":{"margin":-2.86,"winner":"REP","dem_votes":3569,"rep_votes":3785,"other_votes":199,"total_votes":7553,"dem_pct":47.25,"rep_pct":50.11},"45019":{"margin":7.86,"winner":"DEM","dem_votes":89048,"rep_votes":75233,"other_votes":11569,"total_votes":175850,"dem_pct":50.64,"rep_pct":42.78},"45021":{"margin":-41.72,"winner":"REP","dem_votes":6089,"rep_votes":15165,"other_votes":500,"total_votes":21754,"dem_pct":27.99,"rep_pct":69.71},"45023":{"margin":-4.85,"winner":"REP","dem_votes":6582,"rep_votes":7272,"other_votes":348,"total_votes":14202,"dem_pct":46.35,"rep_pct":51.2},"45025":{"margin":-14.31,"winner":"REP","dem_votes":7125,"rep_votes":9576,"other_votes":427,"total_votes":17128,"dem_pct":41.6,"rep_pct":55.91},"45027":{"margin":2.57,"winner":"DEM","dem_votes":7635,"rep_votes":7246,"other_votes":275,"total_votes":15156,"dem_pct":50.38,"rep_pct":47.81},"45029":{"margin":-8.51,"winner":"REP","dem_votes":7616,"rep_votes":9083,"other_votes":532,"total_votes":17231,"dem_pct":44.2,"rep_pct":52.71},"45031":{"margin":-3.73,"winner":"REP","dem_votes":13866,"rep_votes":14973,"other_votes":797,"total_votes":29636,"dem_pct":46.79,"rep_pct":50.52},"45033":{"margin":1.66,"winner":"DEM","dem_votes":5832,"rep_votes":5637,"other_votes":227,"total_votes":11696,"dem_pct":49.86,"rep_pct":48.2},"45035":{"margin":-17.48,"winner":"REP","dem_votes":24010,"rep_votes":34932,"other_votes":3521,"total_votes":62463,"dem_pct":38.44,"rep_pct":55.92},"45037":{"margin":-20.19,"winner":"REP","dem_votes":4491,"rep_votes":6842,"other_votes":311,"total_votes":11644,"dem_pct":38.57,"rep_pct":58.76},"45039":{"margin":25.88,"winner":"DEM","dem_votes":6936,"rep_votes":4024,"other_votes":292,"total_votes":11252,"dem_pct":61.64,"rep_pct":35.76},"45041":{"margin":-4.96,"winner":"REP","dem_votes":26630,"rep_votes":29498,"other_votes":1642,"total_votes":57770,"dem_pct":46.1,"rep_pct":51.06},"45043":{"margin":-13.01,"winner":"REP","dem_votes":13234,"rep_votes":17334,"other_votes":951,"total_votes":31519,"dem_pct":41.99,"rep_pct":55},"45045":{"margin":-24.7,"winner":"REP","dem_votes":73338,"rep_votes":125595,"other_votes":12639,"total_votes":211572,"dem_pct":34.66,"rep_pct":59.36},"45047":{"margin":-21.84,"winner":"REP","dem_votes":10633,"rep_votes":16881,"other_votes":1086,"total_votes":28600,"dem_pct":37.18,"rep_pct":59.02},"45049":{"margin":19.1,"winner":"DEM","dem_votes":5163,"rep_votes":3483,"other_votes":148,"total_votes":8794,"dem_pct":58.71,"rep_pct":39.61},"45051":{"margin":-37.82,"winner":"REP","dem_votes":36731,"rep_votes":83819,"other_votes":3953,"total_votes":124503,"dem_pct":29.5,"rep_pct":67.32},"45053":{"margin":11.88,"winner":"DEM","dem_votes":7789,"rep_votes":6100,"other_votes":327,"total_votes":14216,"dem_pct":54.79,"rep_pct":42.91},"45055":{"margin":-24.83,"winner":"REP","dem_votes":10293,"rep_votes":17464,"other_votes":1118,"total_votes":28875,"dem_pct":35.65,"rep_pct":60.48},"45057":{"margin":-25.52,"winner":"REP","dem_votes":13718,"rep_votes":23598,"other_votes":1401,"total_votes":38717,"dem_pct":35.43,"rep_pct":60.95},"45059":{"margin":-29.94,"winner":"REP","dem_votes":8845,"rep_votes":16770,"other_votes":859,"total_votes":26474,"dem_pct":33.41,"rep_pct":63.35},"45061":{"margin":29.36,"winner":"DEM","dem_votes":5170,"rep_votes":2789,"other_votes":151,"total_votes":8110,"dem_pct":63.75,"rep_pct":34.39},"45063":{"margin":-36.71,"winner":"REP","dem_votes":35143,"rep_votes":79866,"other_votes":6820,"total_votes":121829,"dem_pct":28.85,"rep_pct":65.56},"45065":{"margin":-3.29,"winner":"REP","dem_votes":2479,"rep_votes":2651,"other_votes":85,"total_votes":5215,"dem_pct":47.54,"rep_pct":50.83},"45067":{"margin":21.72,"winner":"DEM","dem_votes":8522,"rep_votes":5434,"other_votes":261,"total_votes":14217,"dem_pct":59.94,"rep_pct":38.22},"45069":{"margin":16.14,"winner":"DEM","dem_votes":5928,"rep_votes":4257,"other_votes":168,"total_votes":10353,"dem_pct":57.26,"rep_pct":41.12},"45071":{"margin":-22.62,"winner":"REP","dem_votes":6212,"rep_votes":10011,"other_votes":572,"total_votes":16795,"dem_pct":36.99,"rep_pct":59.61},"45073":{"margin":-48.06,"winner":"REP","dem_votes":7979,"rep_votes":24096,"other_votes":1455,"total_votes":33530,"dem_pct":23.8,"rep_pct":71.86},"45075":{"margin":36.96,"winner":"DEM","dem_votes":26258,"rep_votes":11909,"other_votes":657,"total_votes":38824,"dem_pct":67.63,"rep_pct":30.67},"45077":{"margin":-52.73,"winner":"REP","dem_votes":10327,"rep_votes":36096,"other_votes":2448,"total_votes":48871,"dem_pct":21.13,"rep_pct":73.86},"45079":{"margin":32.85,"winner":"DEM","dem_votes":108401,"rep_votes":52753,"other_votes":8246,"total_votes":169400,"dem_pct":63.99,"rep_pct":31.14},"45081":{"margin":-31.73,"winner":"REP","dem_votes":2809,"rep_votes":5525,"other_votes":225,"total_votes":8559,"dem_pct":32.82,"rep_pct":64.55},"45083":{"margin":-29.98,"winner":"REP","dem_votes":39888,"rep_votes":76101,"other_votes":4804,"total_votes":120793,"dem_pct":33.02,"rep_pct":63},"45085":{"margin":12.01,"winner":"DEM","dem_votes":24024,"rep_votes":18733,"other_votes":1291,"total_votes":44048,"dem_pct":54.54,"rep_pct":42.53},"45087":{"margin":-19.28,"winner":"REP","dem_votes":4727,"rep_votes":7058,"other_votes":302,"total_votes":12087,"dem_pct":39.11,"rep_pct":58.39},"45089":{"margin":33.8,"winner":"DEM","dem_votes":9949,"rep_votes":4863,"other_votes":237,"total_votes":15049,"dem_pct":66.11,"rep_pct":32.31},"45091":{"margin":-22.05,"winner":"REP","dem_votes":41230,"rep_votes":66245,"other_votes":5950,"total_votes":113425,"dem_pct":36.35,"rep_pct":58.4}}},"2020":{"candidates":{"dem":"Joe Biden","rep":"Donald Trump"},"counties":{"45001":{"margin":-33.09,"winner":"REP","dem_votes":4101,"rep_votes":8215,"other_votes":117,"total_votes":12433,"dem_pct":32.98,"rep_pct":66.07},"45003":{"margin":-22.67,"winner":"REP","dem_votes":32275,"rep_votes":51589,"other_votes":1321,"total_votes":85185,"dem_pct":37.89,"rep_pct":60.56},"45005":{"margin":52.41,"winner":"DEM","dem_votes":2718,"rep_votes":835,"other_votes":40,"total_votes":3593,"dem_pct":75.65,"rep_pct":23.24},"45007":{"margin":-42.04,"winner":"REP","dem_votes":27169,"rep_votes":67565,"other_votes":1359,"total_votes":96093,"dem_pct":28.27,"rep_pct":70.31},"45009":{"margin":24.57,"winner":"DEM","dem_votes":4010,"rep_votes":2417,"other_votes":55,"total_votes":6482,"dem_pct":61.86,"rep_pct":37.29},"45011":{"margin":-7.48,"winner":"REP","dem_votes":4720,"rep_votes":5492,"other_votes":109,"total_votes":10321,"dem_pct":45.73,"rep_pct":53.21},"45013":{"margin":-9.99,"winner":"REP","dem_votes":43419,"rep_votes":53194,"other_votes":1222,"total_votes":97835,"dem_pct":44.38,"rep_pct":54.37},"45015":{"margin":-11.66,"winner":"REP","dem_votes":45223,"rep_votes":57397,"other_votes":1838,"total_votes":104458,"dem_pct":43.29,"rep_pct":54.95},"45017":{"margin":-4.82,"winner":"REP","dem_votes":3905,"rep_votes":4305,"other_votes":81,"total_votes":8291,"dem_pct":47.1,"rep_pct":51.92},"45019":{"margin":12.88,"winner":"DEM","dem_votes":121485,"rep_votes":93297,"other_votes":4075,"total_votes":218857,"dem_pct":55.51,"rep_pct":42.63},"45021":{"margin":-43.77,"winner":"REP","dem_votes":6983,"rep_votes":18043,"other_votes":244,"total_votes":25270,"dem_pct":27.63,"rep_pct":71.4},"45023":{"margin":-10.91,"winner":"REP","dem_votes":6941,"rep_votes":8660,"other_votes":156,"total_votes":15757,"dem_pct":44.05,"rep_pct":54.96},"45025":{"margin":-20.48,"winner":"REP","dem_votes":7431,"rep_votes":11297,"other_votes":148,"total_votes":18876,"dem_pct":39.37,"rep_pct":59.85},"45027":{"margin":-0.67,"winner":"REP","dem_votes":8250,"rep_votes":8361,"other_votes":122,"total_votes":16733,"dem_pct":49.3,"rep_pct":49.97},"45029":{"margin":-9.53,"winner":"REP","dem_votes":8602,"rep_votes":10440,"other_votes":241,"total_votes":19283,"dem_pct":44.61,"rep_pct":54.14},"45031":{"margin":-4.97,"winner":"REP","dem_votes":15220,"rep_votes":16832,"other_votes":365,"total_votes":32417,"dem_pct":46.95,"rep_pct":51.92},"45033":{"margin":-1.11,"winner":"REP","dem_votes":6436,"rep_votes":6582,"other_votes":83,"total_votes":13101,"dem_pct":49.13,"rep_pct":50.24},"45035":{"margin":-10.47,"winner":"REP","dem_votes":33824,"rep_votes":41913,"other_votes":1541,"total_votes":77278,"dem_pct":43.77,"rep_pct":54.24},"45037":{"margin":-24.29,"winner":"REP","dem_votes":4953,"rep_votes":8184,"other_votes":167,"total_votes":13304,"dem_pct":37.23,"rep_pct":61.52},"45039":{"margin":22.72,"winner":"DEM","dem_votes":7382,"rep_votes":4625,"other_votes":129,"total_votes":12136,"dem_pct":60.83,"rep_pct":38.11},"45041":{"margin":-2.27,"winner":"REP","dem_votes":31153,"rep_votes":32615,"other_votes":742,"total_votes":64510,"dem_pct":48.29,"rep_pct":50.56},"45043":{"margin":-12.72,"winner":"REP","dem_votes":15822,"rep_votes":20487,"other_votes":359,"total_votes":36668,"dem_pct":43.15,"rep_pct":55.87},"45045":{"margin":-18.2,"winner":"REP","dem_votes":103030,"rep_votes":150021,"other_votes":5104,"total_votes":258155,"dem_pct":39.91,"rep_pct":58.11},"45047":{"margin":-22.76,"winner":"REP","dem_votes":12145,"rep_votes":19431,"other_votes":430,"total_votes":32006,"dem_pct":37.95,"rep_pct":60.71},"45049":{"margin":15.23,"winner":"DEM","dem_votes":5323,"rep_votes":3906,"other_votes":76,"total_votes":9305,"dem_pct":57.21,"rep_pct":41.98},"45051":{"margin":-33.19,"winner":"REP","dem_votes":59180,"rep_votes":118821,"other_votes":1743,"total_votes":179744,"dem_pct":32.92,"rep_pct":66.11},"45053":{"margin":0.75,"winner":"DEM","dem_votes":7185,"rep_votes":7078,"other_votes":131,"total_votes":14394,"dem_pct":49.92,"rep_pct":49.17},"45055":{"margin":-23.11,"winner":"REP","dem_votes":12699,"rep_votes":20471,"other_votes":459,"total_votes":33629,"dem_pct":37.76,"rep_pct":60.87},"45057":{"margin":-22.81,"winner":"REP","dem_votes":18937,"rep_votes":30312,"other_votes":619,"total_votes":49868,"dem_pct":37.97,"rep_pct":60.78},"45059":{"margin":-32.29,"winner":"REP","dem_votes":10159,"rep_votes":20004,"other_votes":325,"total_votes":30488,"dem_pct":33.32,"rep_pct":65.61},"45061":{"margin":27.53,"winner":"DEM","dem_votes":5329,"rep_votes":3008,"other_votes":94,"total_votes":8431,"dem_pct":63.21,"rep_pct":35.68},"45063":{"margin":-30.1,"winner":"REP","dem_votes":49301,"rep_votes":92817,"other_votes":2450,"total_votes":144568,"dem_pct":34.1,"rep_pct":64.2},"45065":{"margin":-4.75,"winner":"REP","dem_votes":2687,"rep_votes":2958,"other_votes":52,"total_votes":5697,"dem_pct":47.17,"rep_pct":51.92},"45067":{"margin":21.5,"winner":"DEM","dem_votes":8872,"rep_votes":5711,"other_votes":121,"total_votes":14704,"dem_pct":60.34,"rep_pct":38.84},"45069":{"margin":10.88,"winner":"DEM","dem_votes":6290,"rep_votes":5044,"other_votes":112,"total_votes":11446,"dem_pct":54.95,"rep_pct":44.07},"45071":{"margin":-24.07,"winner":"REP","dem_votes":6958,"rep_votes":11443,"other_votes":230,"total_votes":18631,"dem_pct":37.35,"rep_pct":61.42},"45073":{"margin":-47.42,"winner":"REP","dem_votes":10414,"rep_votes":29698,"other_votes":556,"total_votes":40668,"dem_pct":25.61,"rep_pct":73.03},"45075":{"margin":33.23,"winner":"DEM","dem_votes":27295,"rep_votes":13603,"other_votes":307,"total_votes":41205,"dem_pct":66.24,"rep_pct":33.01},"45077":{"margin":-50.85,"winner":"REP","dem_votes":13645,"rep_votes":42907,"other_votes":994,"total_votes":57546,"dem_pct":23.71,"rep_pct":74.56},"45079":{"margin":38.31,"winner":"DEM","dem_votes":132570,"rep_votes":58313,"other_votes":2939,"total_votes":193822,"dem_pct":68.4,"rep_pct":30.09},"45081":{"margin":-35.01,"winner":"REP","dem_votes":2963,"rep_votes":6210,"other_votes":101,"total_votes":9274,"dem_pct":31.95,"rep_pct":66.96},"45083":{"margin":-27.34,"winner":"REP","dem_votes":52926,"rep_votes":93560,"other_votes":2169,"total_votes":148655,"dem_pct":35.6,"rep_pct":62.94},"45085":{"margin":13.04,"winner":"DEM","dem_votes":27379,"rep_votes":21000,"other_votes":541,"total_votes":48920,"dem_pct":55.97,"rep_pct":42.93},"45087":{"margin":-24.5,"winner":"REP","dem_votes":4935,"rep_votes":8183,"other_votes":139,"total_votes":13257,"dem_pct":37.23,"rep_pct":61.73},"45089":{"margin":29.76,"winner":"DEM","dem_votes":10289,"rep_votes":5532,"other_votes":164,"total_votes":15985,"dem_pct":64.37,"rep_pct":34.61},"45091":{"margin":-16.47,"winner":"REP","dem_votes":59008,"rep_votes":82727,"other_votes":2315,"total_votes":144050,"dem_pct":40.96,"rep_pct":57.43}}},"2024":{"candidates":{"dem":"Kamala Harris","rep":"Donald Trump"},"counties":{"45001":{"margin":-42.42,"winner":"REP","dem_votes":3399,"rep_votes":8509,"other_votes":140,"total_votes":12048,"dem_pct":28.21,"rep_pct":70.63},"45003":{"margin":-25.9,"winner":"REP","dem_votes":31298,"rep_votes":53592,"other_votes":1201,"total_votes":86091,"dem_pct":36.35,"rep_pct":62.25},"45005":{"margin":44.73,"winner":"DEM","dem_votes":2165,"rep_votes":813,"other_votes":45,"total_votes":3023,"dem_pct":71.62,"rep_pct":26.89},"45007":{"margin":-47.35,"winner":"REP","dem_votes":25281,"rep_votes":71828,"other_votes":1187,"total_votes":98296,"dem_pct":25.72,"rep_pct":73.07},"45009":{"margin":15.26,"winner":"DEM","dem_votes":3245,"rep_votes":2376,"other_votes":73,"total_votes":5694,"dem_pct":56.99,"rep_pct":41.73},"45011":{"margin":-15.54,"winner":"REP","dem_votes":4082,"rep_votes":5605,"other_votes":116,"total_votes":9803,"dem_pct":41.64,"rep_pct":57.18},"45013":{"margin":-14.48,"winner":"REP","dem_votes":44002,"rep_votes":59123,"other_votes":1278,"total_votes":104403,"dem_pct":42.15,"rep_pct":56.63},"45015":{"margin":-16.27,"winner":"REP","dem_votes":46416,"rep_votes":64777,"other_votes":1641,"total_votes":112834,"dem_pct":41.14,"rep_pct":57.41},"45017":{"margin":-14.34,"winner":"REP","dem_votes":3339,"rep_votes":4474,"other_votes":101,"total_votes":7914,"dem_pct":42.19,"rep_pct":56.53},"45019":{"margin":5.67,"winner":"DEM","dem_votes":111427,"rep_votes":99265,"other_votes":3829,"total_votes":214521,"dem_pct":51.94,"rep_pct":46.27},"45021":{"margin":-51.36,"winner":"REP","dem_votes":5939,"rep_votes":18697,"other_votes":203,"total_votes":24839,"dem_pct":23.91,"rep_pct":75.27},"45023":{"margin":-17.21,"winner":"REP","dem_votes":6353,"rep_votes":9030,"other_votes":173,"total_votes":15556,"dem_pct":40.84,"rep_pct":58.05},"45025":{"margin":-28.07,"winner":"REP","dem_votes":6520,"rep_votes":11682,"other_votes":189,"total_votes":18391,"dem_pct":35.45,"rep_pct":63.52},"45027":{"margin":-12.27,"winner":"REP","dem_votes":7064,"rep_votes":9065,"other_votes":191,"total_votes":16320,"dem_pct":43.28,"rep_pct":55.55},"45029":{"margin":-18.16,"winner":"REP","dem_votes":7376,"rep_votes":10696,"other_votes":204,"total_votes":18276,"dem_pct":40.36,"rep_pct":58.52},"45031":{"margin":-13.32,"winner":"REP","dem_votes":12977,"rep_votes":17017,"other_votes":337,"total_votes":30331,"dem_pct":42.78,"rep_pct":56.1},"45033":{"margin":-10.83,"winner":"REP","dem_votes":5241,"rep_votes":6526,"other_votes":94,"total_votes":11861,"dem_pct":44.19,"rep_pct":55.02},"45035":{"margin":-14.59,"winner":"REP","dem_votes":32489,"rep_votes":43839,"other_votes":1436,"total_votes":77764,"dem_pct":41.78,"rep_pct":56.37},"45037":{"margin":-31.85,"winner":"REP","dem_votes":4659,"rep_votes":9092,"other_votes":168,"total_votes":13919,"dem_pct":33.47,"rep_pct":65.32},"45039":{"margin":13.24,"winner":"DEM","dem_votes":6277,"rep_votes":4792,"other_votes":146,"total_votes":11215,"dem_pct":55.97,"rep_pct":42.73},"45041":{"margin":-8.02,"winner":"REP","dem_votes":27706,"rep_votes":32615,"other_votes":819,"total_votes":61140,"dem_pct":45.32,"rep_pct":53.34},"45043":{"margin":-19.5,"winner":"REP","dem_votes":14965,"rep_votes":22326,"other_votes":463,"total_votes":37754,"dem_pct":39.64,"rep_pct":59.14},"45045":{"margin":-22.2,"winner":"REP","dem_votes":100074,"rep_votes":158541,"other_votes":4701,"total_votes":263316,"dem_pct":38.01,"rep_pct":60.21},"45047":{"margin":-28.98,"winner":"REP","dem_votes":10766,"rep_votes":19715,"other_votes":407,"total_votes":30888,"dem_pct":34.85,"rep_pct":63.83},"45049":{"margin":6.4,"winner":"DEM","dem_votes":4328,"rep_votes":3801,"other_votes":104,"total_votes":8233,"dem_pct":52.57,"rep_pct":46.17},"45051":{"margin":-38.55,"winner":"REP","dem_votes":62325,"rep_votes":141719,"other_votes":1910,"total_votes":205954,"dem_pct":30.26,"rep_pct":68.81},"45053":{"margin":-9.64,"winner":"REP","dem_votes":8144,"rep_votes":9900,"other_votes":183,"total_votes":18227,"dem_pct":44.68,"rep_pct":54.32},"45055":{"margin":-28.22,"winner":"REP","dem_votes":11826,"rep_votes":21289,"other_votes":418,"total_votes":33533,"dem_pct":35.27,"rep_pct":63.49},"45057":{"margin":-24.77,"winner":"REP","dem_votes":20146,"rep_votes":33623,"other_votes":658,"total_votes":54427,"dem_pct":37.01,"rep_pct":61.78},"45059":{"margin":-40.85,"winner":"REP","dem_votes":8769,"rep_votes":21110,"other_votes":334,"total_votes":30213,"dem_pct":29.02,"rep_pct":69.87},"45061":{"margin":17.67,"winner":"DEM","dem_votes":4505,"rep_votes":3078,"other_votes":493,"total_votes":8076,"dem_pct":55.78,"rep_pct":38.11},"45063":{"margin":-33.46,"winner":"REP","dem_votes":47815,"rep_votes":96965,"other_votes":2123,"total_votes":146903,"dem_pct":32.55,"rep_pct":66.01},"45065":{"margin":-17.1,"winner":"REP","dem_votes":2513,"rep_votes":3565,"other_votes":75,"total_votes":6153,"dem_pct":40.84,"rep_pct":57.94},"45067":{"margin":10.54,"winner":"DEM","dem_votes":7316,"rep_votes":5906,"other_votes":166,"total_votes":13388,"dem_pct":54.65,"rep_pct":44.11},"45069":{"margin":2.37,"winner":"DEM","dem_votes":5137,"rep_votes":4896,"other_votes":119,"total_votes":10152,"dem_pct":50.6,"rep_pct":48.23},"45071":{"margin":-34.34,"winner":"REP","dem_votes":5841,"rep_votes":12067,"other_votes":221,"total_votes":18129,"dem_pct":32.22,"rep_pct":66.56},"45073":{"margin":-51.55,"winner":"REP","dem_votes":9987,"rep_votes":31772,"other_votes":505,"total_votes":42264,"dem_pct":23.63,"rep_pct":75.18},"45075":{"margin":24.57,"winner":"DEM","dem_votes":22832,"rep_votes":13750,"other_votes":388,"total_votes":36970,"dem_pct":61.76,"rep_pct":37.19},"45077":{"margin":-52.66,"winner":"REP","dem_votes":13891,"rep_votes":45728,"other_votes":832,"total_votes":60451,"dem_pct":22.98,"rep_pct":75.64},"45079":{"margin":34.58,"winner":"DEM","dem_votes":121110,"rep_votes":58019,"other_votes":3282,"total_votes":182411,"dem_pct":66.39,"rep_pct":31.81},"45081":{"margin":-44.36,"winner":"REP","dem_votes":2454,"rep_votes":6452,"other_votes":108,"total_votes":9014,"dem_pct":27.22,"rep_pct":71.58},"45083":{"margin":-33.63,"winner":"REP","dem_votes":50710,"rep_votes":103032,"other_votes":1855,"total_votes":155597,"dem_pct":32.59,"rep_pct":66.22},"45085":{"margin":4.89,"winner":"DEM","dem_votes":23425,"rep_votes":21215,"other_votes":530,"total_votes":45170,"dem_pct":51.86,"rep_pct":46.97},"45087":{"margin":-32.7,"winner":"REP","dem_votes":4084,"rep_votes":8102,"other_votes":103,"total_votes":12289,"dem_pct":33.23,"rep_pct":65.93},"45089":{"margin":21.7,"winner":"DEM","dem_votes":8634,"rep_votes":5524,"other_votes":172,"total_votes":14330,"dem_pct":60.25,"rep_pct":38.55},"45091":{"margin":-19.08,"winner":"REP","dem_votes":59600,"rep_votes":88239,"other_votes":2220,"total_votes":150059,"dem_pct":39.72,"rep_pct":58.8}}}}